{"instruction": "extract event trigger, the entities involved, and the roles that entities have in the event or the relationships between them. Output is in JSON format", "context": "Peraltro, si dà atto dell'intervento di un membro supplente, non indicando i tre componenti, né si fa sua menzione dalla specificazione del membro effettivo sostituito.", "response": "{\"event_trigger\": \"si dà atto dell'intervento\", \"legal_concepts\": null, \"references\": null, \"actors\": [\"membro supplente\", \"membro effettivo sostituito\"], \"keywords\": null, \"roles\": [{\"role_name\": \"theme\", \"argument1\": \"si dà atto dell'intervento\", \"argument2\": \"un membro supplente\"}]}"}
{"instruction": "extract event trigger, the entities involved, and the roles that entities have in the event or the relationships between them. Output is in JSON format", "context": "In sede di procedimento elettorale negli Enti locali siciliani, l'art. 3 comma 6 L. reg.", "response": "{\"event_trigger\": \"procedimento elettorale negli Enti locali siciliani\", \"legal_concepts\": \"Enti locali siciliani\", \"references\": \"art. 3 comma 6 L. reg.\", \"actors\": null, \"keywords\": null, \"roles\": [{\"role_name\": \"regulates\", \"argument1\": \"art. 3 comma 6 L. reg.\", \"argument2\": \"Enti locali siciliani\"}]}"}
{"instruction": "extract event trigger and the roles or relationships of the entities involved in the event. Output is in JSON format", "context": "Fermo restando quanto previsto ai fini della procedura di Valutazione ambientale strategica (VAS), il Piano è costituito dai seguenti elaborati: a) quadro di analisi conoscitivo, suddiviso per bacini di utenza, volto all’analisi della consistenza dei giacimenti in essere sul territorio regionale; b) quadro operativo, che individua i poli estrattivi, i siti per il deposito dei rifiuti di estrazione ardesiaci e le zone ove è consentita la realizzazione di opere in superficie delle cave in sotterraneo, quali imbocchi, strade di servizio, piazzali; c) norme di attuazione, che prevedono in particolare le modalità, le indicazioni e le condizioni per l'esercizio dell'attività estrattiva e per la sistemazione finale dei siti; d) documento di definizione dei contenuti fondamentali del Piano, per la modifica dei quali è necessaria una variante sostanziale, ai sensi dell'articolo 6, comma 1; e) piano di monitoraggio.", "response": "{\"event_trigger\": \"è costituito\", \"roles\": [{\"role_name\": \"agent\", \"argument1\": \"è costituito\", \"argument2\": \"Piano\"}, {\"role_name\": \"theme\", \"argument1\": \"è costituito\", \"argument2\": \"procedura di Valutazione ambientale strategica (VAS)\"}, {\"role_name\": \"regulates\", \"argument1\": \"quadro di analisi conoscitivo\", \"argument2\": [\"bacini di utenza\", \"territorio regionale\", \"analisi della consistenza dei giacimenti\"]}, {\"role_name\": \"regulates\", \"argument1\": \"quadro operativo\", \"argument2\": [\"poli estrattivi\", \"siti per il deposito dei rifiuti di estrazione ardesiaci\", \"zone ove è consentita la realizzazione di opere in superficie delle cave in sotterraneo\", \"imbocchi, strade di servizio, piazzali\"]}, {\"role_name\": \"regulates\", \"argument1\": \"norme di attuazione\", \"argument2\": [\"condizioni per l'esercizio\", \"sistemazione finale dei siti\"]}, {\"role_name\": \"regulates\", \"argument1\": \"documento di definizione dei contenuti fondamentali\", \"argument2\": \"modifica\"}, {\"role_name\": \"regulates\", \"argument1\": \"articolo 6, comma 1\", \"argument2\": \"modifica\"}]}"}
{"instruction": "extract event trigger and the entities involved in the event. Output is in JSON format", "context": "Fermo restando quanto previsto ai fini della procedura di Valutazione ambientale strategica (VAS), il Piano è costituito dai seguenti elaborati: a) quadro di analisi conoscitivo, suddiviso per bacini di utenza, volto all’analisi della consistenza dei giacimenti in essere sul territorio regionale; b) quadro operativo, che individua i poli estrattivi, i siti per il deposito dei rifiuti di estrazione ardesiaci e le zone ove è consentita la realizzazione di opere in superficie delle cave in sotterraneo, quali imbocchi, strade di servizio, piazzali; c) norme di attuazione, che prevedono in particolare le modalità, le indicazioni e le condizioni per l'esercizio dell'attività estrattiva e per la sistemazione finale dei siti; d) documento di definizione dei contenuti fondamentali del Piano, per la modifica dei quali è necessaria una variante sostanziale, ai sensi dell'articolo 6, comma 1; e) piano di monitoraggio.", "response": "{\"event_trigger\": \"è costituito\", \"legal_concepts\": [\"Piano\", \"procedura di Valutazione ambientale strategica (VAS)\", \"quadro di analisi conoscitivo\", \"quadro operativo\", \"norme di attuazione\", \"documento di definizione dei contenuti fondamentali\", \"piano di monitoraggio\"], \"references\": \"articolo 6, comma 1\", \"actors\": null, \"keywords\": [\"bacini di utenza\", \"territorio regionale\", \"analisi della consistenza dei giacimenti\", \"poli estrattivi\", \"siti per il deposito dei rifiuti di estrazione ardesiaci\", \"zone ove è consentita la realizzazione di opere in superficie delle cave in sotterraneo\", \"imbocchi\", \"strade di servizio\", \"piazzali\", \"condizioni per l'esercizio\", \"sistemazione finale dei siti\", \"modifica\"]}"}
{"instruction": "extract event trigger, the entities involved, and the roles that entities have in the event or the relationships between them. Output is in JSON format", "context": "Con l'inserimento nei tracciati “record” di controllo di codici che si assume non rispondenti alla realtà, la struttura avrebbe quindi ottenuto indebiti rimborsi integrali per prestazioni già in parte pagate privatamente dai pazienti e, pertanto, non più aventi le caratteristiche per essere fatturabili all'Azienda Sanitaria.", "response": "{\"event_trigger\": \"ottenuto\", \"legal_concepts\": [\"indebiti rimborsi integrali\", \"fatturabili\"], \"references\": null, \"actors\": [\"la struttura\", \"Azienda Sanitaria\"], \"keywords\": [\"controllo di codici\", \"pazienti\", \"Azienda Sanitaria\"], \"roles\": [{\"role_name\": \"agent\", \"argument1\": \"ottenuto\", \"argument2\": \"la struttura\"}, {\"role_name\": \"theme\", \"argument1\": \"ottenuto\", \"argument2\": \"indebiti rimborsi integrali\"}]}"}
{"instruction": "extract event trigger, the entities involved, and the roles that entities have in the event or the relationships between them. Output is in JSON format", "context": "Al contrario deve ritenersi che un potere sostitutivo potrà trovare applicazione anche nei loro confronti e, riguardo alle competenze già disciplinate dai rispettivi statuti, continueranno nel frattempo ad operare le specifiche tipologie di potere sostitutivi in essi (o nelle norme di attuazione) disciplinate.", "response": "{\"event_trigger\": \"potrà trovare applicazione\", \"legal_concepts\": [\"potere sostitutivo\", \"competenze disciplinate dai rispettivi statuti\", \"specifiche tipologie di potere sostitutivi\"], \"references\": null, \"actors\": null, \"keywords\": \"loro confronti\", \"roles\": [{\"role_name\": \"agent\", \"argument1\": \"potrà trovare applicazione\", \"argument2\": [\"potere sostitutivo\", \"specifiche tipologie di potere sostitutivi\"]}, {\"role_name\": \"theme\", \"argument1\": \"potrà trovare applicazione\", \"argument2\": [\"loro confronti\", \"competenze disciplinate dai rispettivi statuti\"]}]}"}
{"instruction": "extract event trigger, the entities involved, and the roles that entities have in the event or the relationships between them. Output is in JSON format", "context": "In assenza di indicazioni più specifiche, non desumibili nemmeno dalla relazione al decreto legge, il carattere dell’economicità, di derivazione comunitaria, è stato riconosciuto alle attività di beni e servizi destinati ad un determinato mercato.", "response": "{\"event_trigger\": \"riconosciuto\", \"legal_concepts\": [\"carattere dell'economicità\", \"derivazione comunitaria\", \"attività di beni e servizi\", \"determinato mercato\"], \"references\": \"decreto legge\", \"actors\": null, \"keywords\": null, \"roles\": [{\"role_name\": \"theme\", \"argument1\": \"riconosciuto\", \"argument2\": \"carattere dell’economicità\"}, {\"role_name\": \"regulates\", \"argument1\": \"carattere dell’economicità\", \"argument2\": \"attività di beni e servizi destinati ad un determinato mercato\"}]}"}
{"instruction": "extract event trigger, the entities involved, and the roles that entities have in the event or the relationships between them. Output is in JSON format", "context": "CAPO IV ATTUAZIONE E SCAMBIO DI INFORMAZIONI Violazioni e notifica di violazioni 1.", "response": "{\"event_trigger\": null, \"legal_concepts\": [\"violazioni\", \"notifica di violazioni\"], \"references\": null, \"actors\": null, \"keywords\": [\"attuazione\", \"scambio di informazioni\"], \"roles\": null}"}
{"instruction": "extract event trigger, the entities involved, and the roles that entities have in the event or the relationships between them. Output is in JSON format", "context": "Infatti la citata normativa va interpretata nel senso che il nostro legislatore non ha voluto vietare, in senso assoluto, l'uso del termine pelle pelliccia e cuoio per tutti i capi non provenienti da animali, tant' è che termini come finta pelle erano già diffusi prima che entrasse in vigore la l. 112/66, ma, per la tutela del consumatore e per la serietà del traffico, ha voluto imporre ai commercianti un adeguato segno di distinzione tra le pellicce animali e quelle non provenienti da animali.", "response": "{\"event_trigger\": [\"non ha voluto vietare\", \"ha voluto imporre\"], \"legal_concepts\": [\"uso del termine\", \"citata normativa\", \"l. 112/66\", \"tutela del consumatore\", \"serietà del traffico\", \"segno di distinzione\"], \"references\": [\"citata normativa\", \"l. 112/66\"], \"actors\": [\"legislatore\", \"consumatore\", \"commercianti\"], \"keywords\": [\"pelle pelliccia e cuoio\", \"finta pelle\", \"pellicce animali\", \"pellicce non provenienti da animali\"], \"roles\": [{\"role_name\": \"agent\", \"argument1\": \"non ha voluto vietare\", \"argument2\": \"legislatore\"}, {\"role_name\": \"theme\", \"argument1\": \"non ha voluto vietare\", \"argument2\": \"uso del termine\"}, {\"role_name\": \"agent\", \"argument1\": \"ha voluto imporre\", \"argument2\": \"legislatore\"}, {\"role_name\": \"theme\", \"argument1\": \"ha voluto imporre\", \"argument2\": \"segno di distinzione\"}, {\"role_name\": \"regulates\", \"argument1\": \"l. 112/66\", \"argument2\": [\"uso del termine\", \"pelle pelliccia e cuoio\"]}, {\"role_name\": \"regulates\", \"argument1\": \"citata normativa\", \"argument2\": [\"uso del termine\", \"serietà del traffico\", \"segno di distinzione\", \"pellicce animali e pellicce non provenienti da animali\"]}]}"}
{"instruction": "extract event trigger, the entities involved, and the roles that entities have in the event or the relationships between them. Output is in JSON format", "context": "Ebbene, i suesposti precedenti giurisprudenziali proprio per la loro contiguità, rilevanza e uniformità sembrano definitivamente chiarire la situazione in ordine alla legittimità dell’ingiunzione (fiscale) di pagamento ex art. 639/1910 per l’iscrizione di ipoteca analogamente al ruolo.", "response": "{\"event_trigger\": \"sembrano definitivamente chiarire\", \"legal_concepts\": [\"legittimità dell’ingiunzione (fiscale) di pagamento\", \"iscrizione di ipoteca\"], \"references\": \"art. 639/1910\", \"actors\": null, \"keywords\": \"precedenti giurisprudenziali, contiguità, rilevanza, uniformità\", \"roles\": [{\"role_name\": \"agent\", \"argument1\": \"sembrano definitivamente chiarire\", \"argument2\": \"precedenti giurisprudenziali\"}, {\"role_name\": \"theme\", \"argument1\": \"sembrano definitivamente chiarire\", \"argument2\": \"legittimità dell’ingiunzione (fiscale) di pagamento\"}, {\"role_name\": \"regulates\", \"argument1\": \"art. 639/1910\", \"argument2\": [\"legittimità dell’ingiunzione (fiscale) di pagamento\", \"iscrizione di ipoteca\"]}]}"}
{"instruction": "extract event trigger and the entities involved in the event. Output is in JSON format", "context": "In primo luogo, deve essere rilevato che la Regione Liguria ha esteso la portata della norma statale (d.l. 223/2006, art. 3, comma 1, lett. f) ammettendo, la possibilità di esercitare il consumo immediato sul posto, non solo negli esercizi di vicinato, ma anche nei locali di produzione delle imprese artigiane (pasticcerie, gelaterie, pizzerie al taglio), anticipando così l’orientamento del Consiglio dei ministri, che ha inserito questa possibilità nel c.d. terzo pacchetto Bersani (d.d.l. AS 1644).", "response": "{\"event_trigger\": [\"ha esteso\", \"ammette\"], \"legal_concepts\": [\"possibilità di esercitare il consumo immediato sul posto\"], \"references\": [\"norma statale d.l. 223/2006, art. 3, comma 1, lett. f\", \"terzo pacchetto Bersani (d.d.l. AS 1644)\"], \"actors\": \"Regione Liguria\", \"keywords\": [\"consumo immediato sul posto\", \"esercizi di vicinato\", \"locali di produzione delle imprese artigiane\", \"pasticcerie, gelaterie, pizzerie al taglio\"]}"}
{"instruction": "extract event trigger and the roles that entities have in the event or the relationships between them. Output is in JSON format", "context": "In primo luogo, deve essere rilevato che la Regione Liguria ha esteso la portata della norma statale (d.l. 223/2006, art. 3, comma 1, lett. f) ammettendo, la possibilità di esercitare il consumo immediato sul posto, non solo negli esercizi di vicinato, ma anche nei locali di produzione delle imprese artigiane (pasticcerie, gelaterie, pizzerie al taglio), anticipando così l’orientamento del Consiglio dei ministri, che ha inserito questa possibilità nel c.d. terzo pacchetto Bersani (d.d.l. AS 1644).", "response": "{\"event_trigger\": [\"ha esteso\", \"ammette\"], , \"roles\": [{\"role_name\": \"agent\", \"argument1\": \"ha esteso\", \"argument2\": \"Regione Liguria\"}, {\"role_name\": \"theme\", \"argument1\": \"ha esteso\", \"argument2\": \"norma statale d.l. 223/2006, art. 3, comma 1, lett. f\"}, {\"role_name\": \"agent\", \"argument1\": \"ammette\", \"argument2\": \"norma statale d.l. 223/2006, art. 3, comma 1, lett. f\"}, {\"role_name\": \"theme\", \"argument1\": \"ammette\", \"argument2\": \"possibilità di esercitare il consumo immediato sul posto\"}, {\"role_name\": \"regulates\", \"argument1\": \"norma statale d.l. 223/2006, art. 3, comma 1, lett. f\", \"argument2\": [\"possibilità di esercitare il consumo immediato sul posto\", \"esercizi di vicinato\", \"locali di produzione delle imprese artigiane\"]}, {\"role_name\": \"regulates\", \"argument1\": \"terzo pacchetto Bersani (d.d.l. AS 1644)\", \"argument2\": [\"possibilità di esercitare il consumo immediato sul posto\", \"esercizi di vicinato\", \"locali di produzione delle imprese artigiane\"]}]}"}
{"instruction": "extract event trigger, the entities involved, and the roles that entities have in the event or the relationships between them. Output is in JSON format", "context": "Ricorre altresì il Procuratore generale della Repubblica presso la Corte di appello di Cagliari, sezione distaccata di Sassari, che denuncia la erronea applicazione della legge penale non avendo il Tribunale disposto la trasmissione degli atti all'autorità amministrativa per l'irrogazione della relativa sanzione.", "response": "{\"event_trigger\": \"denuncia\", \"legal_concepts\": [\"erronea applicazione della legge penale\", \"trasmissione degli atti\", \"irrogazione della relativa sanzione\"], \"references\": null, \"actors\": [\"Procuratore generale della Repubblica\", \"Corte di appello di Cagliari\", \"Tribunale\", \"autorità amministrativa\"], \"keywords\": \"Sassari\", \"roles\": [{\"role_name\": \"agent\", \"argument1\": \"denuncia\", \"argument2\": \"Procuratore generale della Repubblica\"}, {\"role_name\": \"theme\", \"argument1\": \"denuncia\", \"argument2\": \"erronea applicazione della legge penale\"}]}"}
{"instruction": "extract event trigger, the entities involved, and the roles that entities have in the event or the relationships between them. Output is in JSON format", "context": "Con riguardo a quest'ultimo parametro, ossia l'affidamento diretto del servizio, s'è condivisibilmente affermato (cfr., approfonditamente sul punto, Cons. St., ad. plen.", "response": "{\"event_trigger\": \"s'è condivisibilmente affermato\", \"legal_concepts\": \"affidamento diretto del servizio\", \"references\": \"Cons. St., ad. plen.\", \"actors\": null, \"keywords\": null, \"roles\": null}"}
{"instruction": "extract event trigger and the entities involved in the event. Output is in JSON format", "context": "Le testate periodiche realizzate unicamente su supporto informatico e diffuse unicamente per via telematica ovvero on line, i cui editori non abbiano fatto domanda di provvidenze, contributi o agevolazioni pubbliche e che conseguano ricavi annui da attivita’ editoriale non superiori a 100.000 euro, non sono soggette agli obblighi stabiliti dall’articolo 5 della legge 8 febbraio 1948, n. 47, dall’articolo 1 della legge 5 agosto 1981, n. 416, e successive modificazioni, e dall’articolo 16 della legge 7 marzo 2001, n. 62, e ad esse non si applicano le disposizioni di cui alla delibera dell’Autorita’ per le garanzie nelle comunicazioni n. 666/08/CONS del 26 novembre 2008, e successive modificazioni.", "response": "{\"event_trigger\": \"non sono soggette\", \"legal_concepts\": [\"testate periodiche realizzate unicamente su supporto informatico e diffuse unicamente per via telematica\", \"provvidenze, contributi o agevolazioni pubbliche\", \"ricavi annui\", \"obblighi stabiliti\"], \"references\": [\"legge 8 febbraio 1948, n. 47\", \"legge 5 agosto 1981, n. 416\", \"legge 7 marzo 2001, n. 62\", \"articolo 16 della legge 7 marzo 2001, n. 62\", \"delibera dell’Autorita’ per le garanzie nelle comunicazioni n. 666/08/CONS del 26 novembre 2008\"], \"actors\": [\"testate periodiche\", \"editori\"], \"keywords\": [\"testate periodiche\", \"supporto informatico\", \"via telematica\", \"obblighi stabiliti\"]}"}
{"instruction": "extract event trigger, the entities involved, and the roles that entities have in the event or the relationships between them. Output is in JSON format", "context": "Le testate periodiche realizzate unicamente su supporto informatico e diffuse unicamente per via telematica ovvero on line, i cui editori non abbiano fatto domanda di provvidenze, contributi o agevolazioni pubbliche e che conseguano ricavi annui da attivita’ editoriale non superiori a 100.000 euro, non sono soggette agli obblighi stabiliti dall’articolo 5 della legge 8 febbraio 1948, n. 47, dall’articolo 1 della legge 5 agosto 1981, n. 416, e successive modificazioni, e dall’articolo 16 della legge 7 marzo 2001, n. 62, e ad esse non si applicano le disposizioni di cui alla delibera dell’Autorita’ per le garanzie nelle comunicazioni n. 666/08/CONS del 26 novembre 2008, e successive modificazioni.", "response": "{\"event_trigger\": \"non sono soggette\", \"roles\": [{\"role_name\": \"agent\", \"argument1\": \"non sono soggette\", \"argument2\": \"testate periodiche realizzate unicamente su supporto informatico e diffuse unicamente per via telematica\"}, {\"role_name\": \"theme\", \"argument1\": \"non sono soggette\", \"argument2\": \"obblighi stabiliti\"}, {\"role_name\": \"regulates\", \"argument1\": [\"legge 8 febbraio 1948, n. 47\", \"legge 5 agosto 1981, n. 416\", \"legge 7 marzo 2001, n. 62\", \"articolo 16 della legge 7 marzo 2001, n. 62\", \"delibera dell’Autorita’ per le garanzie nelle comunicazioni n. 666/08/CONS del 26 novembre 2008\"], \"argument2\": \"obblighi stabiliti\"}, {\"role_name\": \"regulates\", \"argument1\": [\"provvidenze, contributi o agevolazioni pubbliche\", \"ricavi annui\"], \"argument2\": \"editori\"}]}"}
{"instruction": "extract event trigger, the entities involved, and the roles that entities have in the event or the relationships between them. Output is in JSON format", "context": "Secondo: l’ordinamento deve consentire che qualche particolare azione strumentale che durante la fase deliberativa aveva pensato essere corretta si riveli di fatto scorretta, o viceversa, se uno dei partecipanti sia in grado di provarlo in seguito.", "response": "{\"event_trigger\": [\"consentire\", \"si riveli\"], \"legal_concepts\": [\"ordine giuridico\", \"azione strumentale\", \"fase deliberativa\", \"corretta\", \"scorretta\"], \"references\": null, \"actors\": \"partecipanti\", \"keywords\": null, \"roles\": [{\"role_name\": \"agent\", \"argument1\": \"consentire\", \"argument2\": \"ordinamento\"}, {\"role_name\": \"theme\", \"argument1\": \"consentire\", \"argument2\": \"azione strumentale\"}, {\"role_name\": \"agent\", \"argument1\": \"si riveli\", \"argument2\": \"azione strumentale\"}, {\"role_name\": \"theme\", \"argument1\": \"si riveli\", \"argument2\": \"scorretta\"}]}"}
{"instruction": "extract event trigger, the entities involved, and the roles that entities have in the event or the relationships between them. Output is in JSON format", "context": "A volte, il legislatore regionale è affetto da miopia e bada solo a fare cassa senza pensare ad altro.", "response": "{\"event_trigger\": \"bada\", \"legal_concepts\": null, \"references\": null, \"actors\": [\"legislatore regionale\"], \"keywords\": [\"miopia\", \"fare cassa\"], \"roles\": [{\"role_name\": \"agent\", \"argument1\": \"bada\", \"argument2\": \"legislatore regionale\"}, {\"role_name\": \"agent\", \"argument1\": \"bada\", \"argument2\": \"fare cassa\"}]}"}
{"instruction": "extract event trigger, the entities involved, and the roles that entities have in the event or the relationships between them. Output is in JSON format", "context": "Proprio in materia di “controllo analogo”, i giudici di Palazzo Spada, dopo aver diligentemente elencato tutti gli arresti della Corte di giustizia intervenuti sull’argomento, a cominciare dalla sentenza “Stadt Halle” dell’11 gennaio 2005, hanno confermato che non può sussistere il requisito in parola in quei casi in cui si dia vita ad un modulo societario misto, ancorché a partecipazione privata estremamente ridotta.", "response": "{\"event_trigger\": \"hanno confermato che non può sussistere\", \"legal_concepts\": [\"controllo analogo\", \"requisito in parola\", \"modulo societario misto\", \"partecipazione privata\"], \"references\": \"sentenza Stadt Halle dell'11 gennaio 2005\", \"actors\": [\"giudici di Palazzo Spada\", \"Corte di giustizia\"], \"keywords\": [\"arresti\", \"modulo societario misto\", \"partecipazione privata estremamente ridotta\"], \"roles\": [{\"role_name\": \"agent\", \"argument1\": \"hanno confermato che non può sussistere\", \"argument2\": \"giudici di Palazzo Spada\"}, {\"role_name\": \"theme\", \"argument1\": \"hanno confermato che non può sussistere\", \"argument2\": \"requisito in parola\"}, {\"role_name\": \"regulates\", \"argument1\": \"modulo societario misto\", \"argument2\": \"requisito in parola\"}]}"}
{"instruction": "extract event trigger, the entities involved, and the roles that entities have in the event or the relationships between them. Output is in JSON format", "context": "Regola, di ordine generale: Non soggetti a legalizzazione gli atti, documenti, copie ed estratti rilasciati da pubblici funzionari o da pubblici ufficiali (3) (Quando deviano essere prodotti ad organi della pubblica amministrazione, nonché gestori di servizi pubblici, italiani (art. 2 d.P.R. 28 dicembre 2000, n. 445 e succ. modif.).", "response": "{\"event_trigger\": \"Non sono soggetti a legalizzazione\", \"legal_concepts\": [\"atti, documenti, copie ed estratti rilasciati da pubblici funzionari o pubblici ufficiali\", \"organi della pubblica amministrazione\", \"gestori di servizi pubblici, italiani\"], \"references\": \"art. 2 d.P.R. 28 dicembre 2000, n. 445 e succ. modif.\", \"actors\": [\"pubblici funzionari\", \"pubblici ufficiali\", \"organi della pubblica amministrazione\", \"gestori di servizi pubblici\"], \"keywords\": [\"legalizzazione\", \"prodotti\", \"pubblica amministrazione\"], \"roles\": [{\"role_name\": \"theme\", \"argument1\": \"Non sono soggetti a legalizzazione\", \"argument2\": \"atti, documenti, copie ed estratti rilasciati da pubblici funzionari o pubblici ufficiali\"}, {\"role_name\": \"regulates\", \"argument1\": \"art. 2 d.P.R. 28 dicembre 2000, n. 445 e succ. modif.\", \"argument2\": [\"atti, documenti, copie ed estratti rilasciati da pubblici funzionari o pubblici ufficiali\", \"organi della pubblica amministrazione\", \"gestori di servizi pubblici, italiani\"]}]}"}
{"instruction": "extract event trigger, the entities involved, and the roles that entities have in the event or the relationships between them. Output is in JSON format", "context": "Orbene, come è già stato giudicato dalla Corte, il fatto che tale definizione colleghi l’esercizio di un’attività economica alla presenza di risorse umane dimostra che sono necessarie un minimo di organizzazione e una certa stabilità e che di conseguenza, a contrario, la mera presenza di singoli beni o di conti bancari non soddisfa, in linea di principio, i requisiti necessari ai fini della qualificazione come «dipendenza» (sentenza Interedil, C‑396/09, EU:C:2011:671, punto 62).", "response": "{\"event_trigger\": [\"dimostra che sono necessarie\", \"non soddisfa\"], \"legal_concepts\": [\"definizione\", \"esercizio di attività economica\", \"presenza di risorse umane\", \"organizzazione\", \"stabilità\", \"presenza di singoli beni o di conti bancari\", \"requisiti necessari\", \"qualificazione\", \"dipendenza\"], \"references\": \"sentenza Interedil, C‑396/09, EU:C:2011:671\", \"actors\": \"Corte\", \"keywords\": null, \"roles\": [{\"role_name\": \"agent\", \"argument1\": \"dimostra che sono necessarie\", \"argument2\": \"esercizio di attività economica\"}, {\"role_name\": \"agent\", \"argument1\": \"dimostra che sono necessarie\", \"argument2\": \"presenza di risorse umane\"}, {\"role_name\": \"theme\", \"argument1\": \"dimostra che sono necessarie\", \"argument2\": \"requisiti\"}, {\"role_name\": \"agent\", \"argument1\": \"non soddisfa\", \"argument2\": \"presenza di singoli beni o di conti bancari\"}, {\"role_name\": \"theme\", \"argument1\": \"non soddisfa\", \"argument2\": \"requisiti\"}, {\"role_name\": \"regulates\", \"argument1\": \"requisiti\", \"argument2\": [\"qualificazione\", \"dipendenza\"]}, {\"role_name\": \"regulates\", \"argument1\": \"sentenza Interedil, C‑396/09, EU:C:2011:671\", \"argument2\": \"dimostra\"}]}"}
{"instruction": "extract event trigger, the entities involved, and the roles that entities have in the event or the relationships between them. Output is in JSON format", "context": "Violazione e falsa applicazione delle Direttive 77/187/CEE e 92/50/CEE.", "response": "{\"event_trigger\": \"violazione e falsa applicazione\", \"legal_concepts\": [\"Direttive 77/187/CEE\", \"Direttive 92/50/CEE\"], \"references\": \"77/187/CEE, 92/50/CEE\", \"actors\": null, \"keywords\": null, \"roles\": [{\"role_name\": \"theme\", \"argument1\": \"violazione e falsa applicazione\", \"argument2\": [\"Direttive 77/187/CEE\", \"Direttive 92/50/CEE\"]}]}"}
{"instruction": "extract event trigger, the entities involved, and the roles that entities have in the event or the relationships between them. Output is in JSON format", "context": "La deliberazione parlamentare di bilancio, basata sulle UPB, viene ad essere variata attraverso atti amministrativi, che finiscono per alterare significativamente il piano finanziario di inizio d’anno.", "response": "{\"event_trigger\": [\"viene ad essere variata\", \"alterare\"], \"legal_concepts\": [\"deliberazione parlamentare di bilancio\", \"atti amministrativi\", \"UPB\", \"piano finanziario\"], \"references\": null, \"actors\": null, \"keywords\": null, \"roles\": [{\"role_name\": \"agent\", \"argument1\": \"viene ad essere variata\", \"argument2\": \"atti amministrativi\"}, {\"role_name\": \"theme\", \"argument1\": \"viene ad essere variata\", \"argument2\": \"deliberazione parlamentare di bilancio\"}, {\"role_name\": \"agent\", \"argument1\": \"alterare\", \"argument2\": \"atti amministrativi\"}, {\"role_name\": \"theme\", \"argument1\": \"alterare\", \"argument2\": \"piano finanziario\"}, {\"role_name\": \"regulates\", \"argument1\": \"UPB\", \"argument2\": \"deliberazione parlamentare di bilancio\"}]}"}
{"instruction": "extract event trigger and the entities involved in the event. Output is in JSON format", "context": "Incompatibilità 1. Agli incarichi di presidente e di componente del consiglio di amministrazione e del collegio dei revisori si applicano le disposizioni sulla incompatibilità contenute nella vigente normativa nazionale e regionale. In particolare, non può essere nominato presidente e non possono far parte del consiglio di amministrazione e del collegio dei revisori: a) i membri del Consiglio e della Giunta regionali, nonché i sindaci, i presidenti e i membri degli organi esecutivi degli enti locali; b) i direttori generali delle aziende e società che operano nel campo del trasporto pubblico locale, i presidenti e i componenti degli organi di altri enti regionali; c) gli imprenditori o gli amministratori di società che forniscono beni o prestano servizi all'AREMOL; d) i dipendenti dell’amministrazione regionale appartenenti alla struttura preposta alla vigilanza sull'AREMOL; e) i membri degli organi delle organizzazioni professionali e sindacali dei trasporti pubblici.", "response": "{\"event_trigger\": [\"non può essere nominato presidente\", \"non possono far parte del consiglio di amministrazione\"], \"legal_concepts\": \"disposizioni sulla incompatibilità\", \"references\": \"vigente normativa nazionale e regionale\", \"actors\": [\"presidente\", \"consiglio di amministrazione\", \"collegio dei revisori\", \"membri del Consiglio e della Giunta regionali\", \"sindaci\", \"presidenti\", \"membri degli organi esecutivi degli enti locali\", \"direttori generali che operano nel trasporto pubblico locale\", \"società che forniscono beni o prestano servizi all'AREMOL\", \"struttura preposta alla vigilanza sull'AREMOL\", \"organizzazioni professionali e sindacali dei trasporti pubblici\"], \"keywords\": [\"AREMOL\"]}"}
{"instruction": "extract event trigger and the roles that entities have in the event or the relationships between them. Output is in JSON format", "context": "Incompatibilità 1. Agli incarichi di presidente e di componente del consiglio di amministrazione e del collegio dei revisori si applicano le disposizioni sulla incompatibilità contenute nella vigente normativa nazionale e regionale. In particolare, non può essere nominato presidente e non possono far parte del consiglio di amministrazione e del collegio dei revisori: a) i membri del Consiglio e della Giunta regionali, nonché i sindaci, i presidenti e i membri degli organi esecutivi degli enti locali; b) i direttori generali delle aziende e società che operano nel campo del trasporto pubblico locale, i presidenti e i componenti degli organi di altri enti regionali; c) gli imprenditori o gli amministratori di società che forniscono beni o prestano servizi all'AREMOL; d) i dipendenti dell’amministrazione regionale appartenenti alla struttura preposta alla vigilanza sull'AREMOL; e) i membri degli organi delle organizzazioni professionali e sindacali dei trasporti pubblici.", "response": "{\"event_trigger\": [\"non può essere nominato presidente\", \"non possono far parte del consiglio di amministrazione\"], \"roles\": [{\"role_name\": \"agent\", \"argument1\": [\"non può essere nominato presidente\", \"non possono far parte del consiglio di amministrazione\"], \"argument2\": \"disposizioni sulla incompatibilità\"}, {\"role_name\": \"theme\", \"argument1\": [\"non può essere nominato presidente\", \"non possono far parte del consiglio di amministrazione\"], \"argument2\": [\"presidenti\", \"membri degli organi esecutivi degli enti locali\", \"direttori generali che operano nel trasporto pubblico locale\", \"società che forniscono beni o prestano servizi all'AREMOL\", \"struttura preposta alla vigilanza sull'AREMOL\", \"organizzazioni professionali e sindacali dei trasporti pubblici\"]}]}"}
{"instruction": "extract event trigger, the entities involved, and the roles that entities have in the event or the relationships between them. Output is in JSON format", "context": "Titolo I Disposizioni generali Destinazione dei finanziamenti 1. La Giunta regionale provvede alla ripartizione dei fondi assegnati alla Regione, in relazione a ciascuno degli interventi previsti dagli articoli 4, 5 e 7 della presente legge, nel rispetto della deliberazione del CIPE di cui al comma 4 dell’ articolo 9 della legge 10/ 1991.", "response": "{\"event_trigger\": \"provvede\", \"legal_concepts\": [\"ripartizione dei fondi\", \"interventi\", \"deliberazione del CIPE\"], \"references\": [\"articoli 4, 5 e 7 della presente legge\", \"comma 4 dell’articolo 9 della legge 10/ 1991\"], \"actors\": \"Giunta regionale\", \"keywords\": \"interventi\", \"roles\": [{\"role_name\": \"agent\", \"argument1\": \"provvede\", \"argument2\": \"La Giunta regionale\"}, {\"role_name\": \"theme\", \"argument1\": \"provvede\", \"argument2\": \"ripartizione dei fondi\"}, {\"role_name\": \"regulates\", \"argument1\": [\"articoli 4, 5 e 7 della presente legge\", \"comma 4 dell’articolo 9 della legge 10/ 1991\"], \"argument2\": \"ripartizione dei fondi\"}]}"}
{"instruction": "extract event trigger, the entities involved, and the roles that entities have in the event or the relationships between them. Output is in JSON format", "context": "Ministri di culto 1. La Repubblica italiana riconosce il ministero pastorale, diaconale e presbiteriale conferito e riconosciuto dalla CELI. 2. Ai ministri di culto, pastori e laici, nominati dalla CELI e dalle sue Comunità è assicurato il libero esercizio del ministero, nonché il libero svolgimento delle attività di cui all'articolo 22. 3. Ai ministri di culto di cui al comma 2 è riconosciuto il diritto di mantenere il segreto d'ufficio su quanto appreso nello svolgimento del proprio ministero.", "response": "{\"event_trigger\": [\"riconosce\", \"è assicurato\"], \"legal_concepts\": [\"ministero pastorale, diaconale e presbiteriale\", \"libero esercizio del ministero\", \"libero esercizio delle attività\", \"segreto d'ufficio\", \"interventi\", \"deliberazione del CIPE\"], \"references\": [\"articoli 4, 5 e 7 della presente legge\", \"comma 4 dell’articolo 9 della legge 10/ 1991\"], \"actors\": [\"La Repubblica italiana\", \"CELI (Church of the Lutheran Evangelical Church in Italy)\"], \"keywords\": null, \"roles\": [{\"role_name\": \"agent\", \"argument1\": \"riconosce\", \"argument2\": \"La Repubblica italiana\"}, {\"role_name\": \"theme\", \"argument1\": \"riconosce\", \"argument2\": [\"ministero pastorale, diaconale e presbiteriale\", \"segreto d'ufficio\"]}, {\"role_name\": \"agent\", \"argument1\": \"è assicurato\", \"argument2\": \"La Repubblica italiana\"}, {\"role_name\": \"theme\", \"argument1\": \"è assicurato\", \"argument2\": [\"libero esercizio del ministero\", \"libero esercizio delle attività\"]}]}"}
{"instruction": "extract event trigger, the entities involved, and the roles that entities have in the event or the relationships between them. Output is in JSON format", "context": "Al punto 10 del 10' comma dell'art. 10 sono soppresse le parole: \"nonché sulla determinazione di nuovi prezzi\".", "response": "{\"event_trigger\": \"sono soppresse\", \"legal_concepts\": \"determinazione di nuovi prezzi\", \"references\": \"punto 10 del 10' comma dell'art. 10\", \"actors\": null, \"keywords\": \"parole\", \"roles\": [{\"role_name\": \"theme\", \"argument1\": \"sono soppresse\", \"argument2\": [\"punto 10 del 10' comma dell'art. 10\", \"parole\", \"determinazione di nuovi prezzi\"]}]}"}
{"instruction": "extract event trigger and the entities involved in the event. Output is in JSON format", "context": "Copertura finanziaria 1. Alle spese occorrenti per l'attuazione della presente legge si provvede nei limiti delle risorse trasferite dallo Stato ai sensi dell'articolo 7, comma 1, della legge 15 marzo 1997, n. 59 e dell'articolo 7 del d.lgs. 31 marzo 1998, n. 112 e con risorse finanziarie della Regione da determinarsi, annualmente, con le leggi di approvazione dei singoli bilanci. 2. Le disponibilità determinate ai sensi del comma 1 sono corrisposte per le funzioni attribuite in ragione d'anno e con decorrenza dalla data di effettivo trasferimento delle funzioni stesse. 3. La Giunta regionale è autorizzata ad istituire i capitoli occorrenti preordinati ai riflessi della gestione; gli atti adottati sono pubblicati nel B.U.R. entro quindici giorni e comunicati al Consiglio regionale entro gli stessi termini.", "response": "{\"event_trigger\": [\"si provvede\", \"è autorizzata ad istituire\"], \"legal_concepts\": [\"spese occorrenti per l'attuazione\", \"copertura finanziaria\", \"risorse trasferite dallo Stato\", \"risorse finanziarie della Regione\", \"leggi di approvazione dei singoli bilanci\", \"capitoli occorrenti preordinati ai riflessi della gestione\"], \"references\": [\"articolo 7, comma 1, della legge 15 marzo 1997, n. 59\", \"articolo 7 del d.lgs. 31 marzo 1998, n. 112\", \"leggi di approvazione dei singoli bilanci\"], \"actors\": [\"Giunta regionale\", \"B.U.R.\"], \"keywords\": null}"}
{"instruction": "extract event trigger, the entities involved, and the roles that entities have in the event or the relationships between them. Output is in JSON format", "context": "Copertura finanziaria 1. Alle spese occorrenti per l'attuazione della presente legge si provvede nei limiti delle risorse trasferite dallo Stato ai sensi dell'articolo 7, comma 1, della legge 15 marzo 1997, n. 59 e dell'articolo 7 del d.lgs. 31 marzo 1998, n. 112 e con risorse finanziarie della Regione da determinarsi, annualmente, con le leggi di approvazione dei singoli bilanci. 2. Le disponibilità determinate ai sensi del comma 1 sono corrisposte per le funzioni attribuite in ragione d'anno e con decorrenza dalla data di effettivo trasferimento delle funzioni stesse. 3. La Giunta regionale è autorizzata ad istituire i capitoli occorrenti preordinati ai riflessi della gestione; gli atti adottati sono pubblicati nel B.U.R. entro quindici giorni e comunicati al Consiglio regionale entro gli stessi termini.", "response": "{\"event_trigger\": [\"si provvede\", \"è autorizzata ad istituire\"], \"roles\": [{\"role_name\": \"agent\", \"argument1\": \"si provvede\", \"argument2\": [\"risorse trasferite dallo Stato\", \"risorse finanziarie della Regione\"]}, {\"role_name\": \"theme\", \"argument1\": \"si provvede\", \"argument2\": \"spese occorrenti per l'attuazione\"}, {\"role_name\": \"regulates\", \"argument1\": [\"articolo 7, comma 1, della legge 15 marzo 1997, n. 59\", \"articolo 7 del d.lgs. 31 marzo 1998, n. 112\"], \"argument2\": \"risorse trasferite dallo Stato\"}, {\"role_name\": \"regulates\", \"argument1\": \"leggi di approvazione dei singoli bilanci\", \"argument2\": \"risorse finanziarie della Regione\"}, {\"role_name\": \"agent\", \"argument1\": \"è autorizzata ad istituire\", \"argument2\": \"Giunta regionale\"}, {\"role_name\": \"theme\", \"argument1\": \"è autorizzata ad istituire\", \"argument2\": \"capitoli occorrenti preordinati ai riflessi della gestione\"}]}"}
{"instruction": "extract event trigger, the entities involved, and the roles that entities have in the event or the relationships between them. Output is in JSON format", "context": "Utilizzo di aeromobili a pilotaggio remoto da parte del Corpo di polizia penitenziaria 1. All'articolo 5, comma 3-sexies, del decreto-legge 18 febbraio 2015, n. 7, convertito, con modificazioni, dalla legge 17 aprile 2015, n. 43, e' aggiunto, in fine, il seguente periodo: «L'utilizzo di aeromobili a pilotaggio remoto da parte del personale abilitato del Corpo di polizia penitenziaria e' previsto nell'ambito delle funzioni svolte dal predetto personale ai sensi dell'articolo 5 della legge 15 dicembre 1990, n. 395, per assicurare una piu' efficace vigilanza sugli istituti penitenziari e garantire la sicurezza all'interno dei medesimi». 2. All'attuazione delle disposizioni del presente articolo si provvede con le risorse umane, finanziarie e strumentali disponibili a legislazione vigente, senza nuovi o maggiori oneri a carico della finanza pubblica.", "response": "{\"event_trigger\": \"è aggiunto\", \"legal_concepts\": \"Utilizzo di aeromobili a pilotaggio remoto\", \"references\": [\"ARTICOLO AGGIUNTO DALLA LEGGE DI CONVERSIONE 25/6/2020, N. 70\", \"articolo 5, comma 3-sexies, del decreto-legge 18 febbraio 2015, n. 7\", \"legge 17 aprile 2015, n. 43\"], \"actors\": \"Corpo di polizia penitenziaria\", \"keywords\": \"periodo\", \"roles\": [{\"role_name\": \"agent\", \"argument1\": \"è aggiunto\", \"argument2\": \"articolo 5, comma 3-sexies, del decreto-legge 18 febbraio 2015, n. 7\"}, {\"role_name\": \"theme\", \"argument1\": \"è aggiunto\", \"argument2\": \"periodo\"}, {\"role_name\": \"regulates\", \"argument1\": \"periodo\", \"argument2\": \"Utilizzo di aeromobili a pilotaggio remoto\"}, {\"role_name\": \"regulates\", \"argument1\": \"articolo 5 della legge 15 dicembre 1990, n. 395\", \"argument2\": \"Utilizzo di aeromobili a pilotaggio remoto\"}]}"}
{"instruction": "extract event trigger, the entities involved, and the roles that entities have in the event or the relationships between them. Output is in JSON format", "context": "L'art. 1, ultimo comma , legge 11 giugno 1971, n. 426, si limita ad enunciare il divieto di esercitare congiuntamente, e cioè nello stesso \"punto di vendita\", il commercio all'ingrosso e quello al minuto; pertanto, non può dirsi vietato di per sé l'esercizio di tali diverse attività commerciali in locali poco distanti fra loro, purché si tratti di locali distinti.", "response": "{\"event_trigger\": [\"divieto di esercitare congiuntamente\", \"non può dirsi vietato\"], \"legal_concepts\": [\"commercio all'ingrosso\", \"commercio al minuto\", \"locali poco distanti fra loro\", \"locali distinti\"], \"references\": \"art. 1, ultimo comma , legge 11 giugno 1971, n. 426\", \"actors\": null, \"keywords\": [\"punto di vendita\", \"esercizio\"], \"roles\": [{\"role_name\": \"theme\", \"argument1\": \"divieto di esercitare congiuntamente\", \"argument2\": [\"commercio all'ingrosso\", \"commercio al minuto\"]}, {\"role_name\": \"regulates\", \"argument1\": \"divieto di esercitare congiuntamente\"}, {\"role_name\": \"theme\", \"argument1\": \"non può dirsi vietato\", \"argument2\": [\"esercizio\", \"locali poco distanti fra loro\", \"locali distinti\"]}]}"}
{"instruction": "extract event trigger, the entities involved, and the roles that entities have in the event or the relationships between them. Output is in JSON format", "context": "TABELLA Legenda: UP: Ufficio periferico UCCE: Ufficio di coordinamento e controllo dighe in esercizio UCPL: Ufficio di coordinamento e controllo vigilanza lavori UCSR: Ufficio di coordinamento Studi e Ricerche.", "response": "{\"event_trigger\": null, \"legal_concepts\": null, \"references\": null, \"actors\": [\"UP\", \"UCCE\", \"UCPL\", \"UCSR\", \"Ufficio periferico\", \"Ufficio di coordinamento e controllo dighe in esercizio\", \"Ufficio di coordinamento e controllo vigilanza lavori\", \"Ufficio di coordinamento Studi e Ricerche\"], \"keywords\": \"TABELLA\", \"roles\": null}"}
{"instruction": "extract event trigger, the entities involved, and the roles that entities have in the event or the relationships between them. Output is in JSON format", "context": "I centri residenziali studenteschi devono essere progettati con la predisposizione di almeno 100 posti letto, con saloni per riunioni, assemblee e convegni, e sale biblioteca e studio, impianti sportivi e refettorio con una capacità di servizi per almeno 200 persone. Alla consegna, le opere passano in proprietà dei Comuni con destinazione di cui al presente regolamento e con i conseguenti oneri di manutenzione.", "response": "{\"event_trigger\": [\"devono essere progettati con la predisposizione\", \"passano in proprietà\"], \"legal_concepts\": [\"centri residenziali studenteschi\", \"proprietà\", \"destinazione\", \"oneri di manutenzione\"], \"references\": null, \"actors\": \"Comuni\", \"keywords\": [\"posti letto\", \"saloni per riunioni, assemblee e convegni\", \"sale biblioteca e studio\", \"impianti sportivi\", \"refettorio\", \"capacità di servizi\", \"opere\"], \"roles\": [{\"role_name\": \"agent\", \"argument2\": \"devono essere progettati con la predisposizione\", \"argument1\": \"centri residenziali studenteschi\"}, {\"role_name\": \"theme\", \"argument2\": \"devono essere progettati con la predisposizione\", \"argument1\": [\"posti letto\", \"saloni per riunioni, assemblee e convegni\", \"sale biblioteca e studio\", \"impianti sportivi\", \"refettorio\", \"capacità di servizi\"]}, {\"role_name\": \"agent\", \"argument2\": \"passano in proprietà\", \"argument1\": \"Comuni\"}, {\"role_name\": \"theme\", \"argument1\": \"passano in proprietà\", \"argument2\": \"opere\"}]}"}
{"instruction": "extract event trigger, the entities involved, and the roles that entities have in the event or the relationships between them. Output is in JSON format", "context": "E' approvata la graduatoria relativa alla Regione Campania, riportata nell'allegato 1 che costituisce parte integrante del presente decreto.", "response": "{\"event_trigger\": \"approvata\", \"legal_concepts\": \"graduatoria, Regione Campania\", \"references\": \"presente decreto, allegato 1\", \"actors\": null, \"keywords\": null, \"roles\": [{\"role_name\": \"agent\", \"argument1\": \"approvata\", \"argument2\": \"Regione Campania\"}, {\"role_name\": \"theme\", \"argument1\": \"approvata\", \"argument2\": \"graduatoria\"}, {\"role_name\": \"regulates\", \"argument1\": \"allegato 1\", \"argument2\": [\"graduatoria\", \"presente decreto\"]}]}"}
{"instruction": "extract event trigger and the entities involved in the event. Output is in JSON format", "context": "Dei delitti contro l'Amministrazione della giustizia Capo I Dei delitti contro l'attività giudiziaria Patrocinio o consulenza infedele Il patrocinatore  o il consulente tecnico, che, rendendosi infedele ai suoi doveri professionali, arreca nocumento agli interessi della parte da lui difesa, assistita o rappresentata dinanzi all'Autorità giudiziaria, o alla Corte penale internazionale è punito con la reclusione da uno a tre anni e con la multa non inferiore a euro 516. La pena è aumentata: 1) se il colpevole ha commesso il fatto, colludendo con la parte avversaria; 2) se il fatto è stato commesso a danno di un imputato. Si applicano la reclusione da tre a dieci anni e la multa non inferiore a euro 1.032, se il fatto è commesso a danno di persona imputata di un delitto per il quale la legge commina l'ergastolo ovvero la reclusione superiore a cinque anni. Importo elevato dall'art. 113, L 24/11/1981 n. 689. Comma modificato dall'art. 10, L. 20/12/2012 , n. 237.", "response": "{\"event_trigger\": [\"è punito\", \"arreca nocumento\", \"è aumentata\"], \"legal_concepts\": [\"delitto contro l'amministrazione della giustizia\", \"nocumento\", \"interessi della parte difesa, assistita o rappresentata\", \"patrocinio o consulenza infedele\", \"reclusione\", \"multa\", \"pena\"], \"references\": [\"art. 113, L 24/11/1981 n. 689\", \"art. 10, L. 20/12/2012 , n. 237\"], \"actors\": [\"patrocinatore\", \"consulente tecnico\", \"parte avversaria\", \"persona imputata\"], \"keywords\": [\"delitto\", \"amministrazione della giustizia\", \"patrocinio\", \"consulenza infedele\", \"colludendo con la parte avversaria\", \"danno di un imputato\", \"reclusione\", \"multa\"]}"}
{"instruction": "extract event trigger and the roles that entities have in the event or the relationships between them. Output is in JSON format", "context": "Dei delitti contro l'Amministrazione della giustizia Capo I Dei delitti contro l'attività giudiziaria Patrocinio o consulenza infedele Il patrocinatore  o il consulente tecnico, che, rendendosi infedele ai suoi doveri professionali, arreca nocumento agli interessi della parte da lui difesa, assistita o rappresentata dinanzi all'Autorità giudiziaria, o alla Corte penale internazionale è punito con la reclusione da uno a tre anni e con la multa non inferiore a euro 516. La pena è aumentata: 1) se il colpevole ha commesso il fatto, colludendo con la parte avversaria; 2) se il fatto è stato commesso a danno di un imputato. Si applicano la reclusione da tre a dieci anni e la multa non inferiore a euro 1.032, se il fatto è commesso a danno di persona imputata di un delitto per il quale la legge commina l'ergastolo ovvero la reclusione superiore a cinque anni. Importo elevato dall'art. 113, L 24/11/1981 n. 689. Comma modificato dall'art. 10, L. 20/12/2012 , n. 237.", "response": "{\"event_trigger\": [\"è punito\", \"arreca nocumento\", \"è aumentata\"], \"roles\": [{\"role_name\": \"agent\", \"argument1\": \"è punito\", \"argument2\": [\"patrocinatore\", \"il consulente tecnico\"]}, {\"role_name\": \"theme\", \"argument1\": \"è punito\", \"argument2\": [\"reclusione\", \"multa\"]}, {\"role_name\": \"agent\", \"argument1\": \"arreca nocumento\", \"argument2\": [\"patrocinatore\", \"il consulente tecnico\"]}, {\"role_name\": \"theme\", \"argument1\": \"arreca\", \"argument2\": \"interessi della parte difesa, assistita o rappresentata\"}, {\"role_name\": \"agent\", \"argument1\": \"è aumentata\", \"argument2\": \"pena\"}, {\"role_name\": \"theme\", \"argument1\": \"è aumentata\", \"argument2\": [\"colludendo con la parte avversaria\", \"danno di un imputato\"]}, {\"role_name\": \"regulates\", \"argument1\": \"art. 113, L 24/11/1981 n. 689\", \"argument2\": \"multa\"}, {\"role_name\": \"regulates\", \"argument1\": \"art. 10, L. 20/12/2012 , n. 237\", \"argument2\": \"è punito\"}]}"}
{"instruction": "extract event trigger, the entities involved, and the roles that entities have in the event or the relationships between them. Output is in JSON format", "context": "Parte seconda Titolo I Trattamento economico Capo II Buono pasto 1. Il costo del buono pasto sostitutivo del servizio di mensa è pari alla somma che l'ente, l'agenzia nazionale o le altre amministrazioni di cui all'art. 19, comma 5, del d.P.R. n. 465/97 sarebbe tenuto a pagare per ogni pasto, ai sensi del comma 3 dell'art. 50, se optasse per l'istituzione della mensa di servizio. 2. Il segretario ha titolo, secondo le direttive adottate dai singoli enti per il restante personale, ad un buono pasto per ogni giornata in cui presti servizio anche nelle ore pomeridiane.", "response": "{\"event_trigger\": [\"è pari\", \"ha titolo\"], \"legal_concepts\": [\"buono pasto sostitutivo del servizio di mensa\", \"costo del buono pasto\", \"ente\", \"agenzia nazionale\", \"altre amministrazioni\", \"istituzione della mensa di servizio\", \"direttive adottate dai singoli enti\"], \"references\": [\"art. 19, comma 5, del d.P.R. n. 465/97\", \"art. 50, comma 3\"], \"actors\": \"segretario\", \"keywords\": [\"somma\", \"buono pasto\", \"servizio di mensa\", \"costo\", \"ogni giornata\"], \"roles\": [{\"role_name\": \"agent\", \"argument1\": \"è pari\", \"argument2\": \"costo del buono pasto\"}, {\"role_name\": \"theme\", \"argument1\": \"è pari\", \"argument2\": [\"somma\", \"istituzione della mensa di servizio\"]}, {\"role_name\": \"regulates\", \"argument1\": \"d.P.R. n. 465/97, art. 19, comma 5\", \"argument2\": \"ente, agenzia nazionale, altre amministrazioni\"}, {\"role_name\": \"regulates\", \"argument1\": \"art. 50, comma 3\", \"argument2\": [\"somma\", \"istituzione della mensa di servizio\"]}, {\"role_name\": \"agent\", \"argument1\": \"ha titolo\", \"argument2\": \"segretario\"}, {\"role_name\": \"theme\", \"argument1\": \"ha titolo\", \"argument2\": [\"buono pasto\", \"ogni giornata\"]}]}"}
{"instruction": "extract event trigger and the entities involved in the event. Output is in JSON format", "context": "Finalmente è stato raggiunto in sede di Conferenza Unificata lo scorso 24 novembre il fatidico accordo necessario per l’emanazione dei tanto attesi DPCM sui criteri e limiti per le assunzioni di personale a tempo indeterminato per il triennio 2005-2007. Perché la situazione si sblocchi definitivamente è ancora necessaria l’emanazione del vero e proprio Decreto del Presidente del Consiglio dei Ministri e la relativa pubblicazione sulla Gazzetta Ufficiale, per cui l’iter probabilmente si concluderà tra la fine di dicembre e gli inizi di gennaio. In ogni caso l’accordo è raggiunto e, fortunatamente, non si limita al 2005, estendendo la sua validità anche ai prossimi due anni, cosa questa di non poco conto se si considera il ritardo con il quale questo DPCM sarà reso noto. Come disciplinato in Finanziaria, l’accordo riguarda sia la contrazione delle dotazioni organiche che la fissazione dei criteri e dei limiti per le assunzioni a tempo indeterminato e si rivolge a regioni, province, comuni, unioni di comuni, comunità montane e consorzi, oltre agli enti del Servizio Sanitario Nazionale.", "response": "{\"event_trigger\": \"emanazione\", \"legal_concepts\": [\"contrazione delle dotazioni organiche\", \"fissazione dei criteri e dei limiti per le assunzioni a tempo indeterminato\", \"regioni\", \"province\", \"comuni\", \"unioni di comuni\", \"comunità montane\", \"consorzi\", \"Servizio Sanitario Nazionale\", \"Finanziaria\", \"tetto di spesa complessivo\"], \"references\": \"DPCM sui criteri e limiti per le assunzioni di personale a tempo indeterminato per il triennio 2005-2007\", \"actors\": [\"regioni\", \"province\", \"comuni\", \"unioni di comuni\", \"comunità montane\", \"consorzi\", \"Presidente del Consiglio dei Ministri\"], \"keywords\": [\"Conferenza Unificata\", \"Gazzetta Ufficiale\"]}"}
{"instruction": "extract event trigger and the roles that entities have in the event or the relationships between them. Output is in JSON format", "context": "Finalmente è stato raggiunto in sede di Conferenza Unificata lo scorso 24 novembre il fatidico accordo necessario per l’emanazione dei tanto attesi DPCM sui criteri e limiti per le assunzioni di personale a tempo indeterminato per il triennio 2005-2007. Perché la situazione si sblocchi definitivamente è ancora necessaria l’emanazione del vero e proprio Decreto del Presidente del Consiglio dei Ministri e la relativa pubblicazione sulla Gazzetta Ufficiale, per cui l’iter probabilmente si concluderà tra la fine di dicembre e gli inizi di gennaio. In ogni caso l’accordo è raggiunto e, fortunatamente, non si limita al 2005, estendendo la sua validità anche ai prossimi due anni, cosa questa di non poco conto se si considera il ritardo con il quale questo DPCM sarà reso noto. Come disciplinato in Finanziaria, l’accordo riguarda sia la contrazione delle dotazioni organiche che la fissazione dei criteri e dei limiti per le assunzioni a tempo indeterminato e si rivolge a regioni, province, comuni, unioni di comuni, comunità montane e consorzi, oltre agli enti del Servizio Sanitario Nazionale.", "response": "{\"event_trigger\": \"emanazione\", \"roles\": [{\"role_name\": \"theme\", \"argument1\": \"emanazione\", \"argument2\": \"DPCM sui criteri e limiti per le assunzioni di personale a tempo indeterminato per il triennio 2005-2007\"}, {\"role_name\": \"regulates\", \"argument1\": \"DPCM sui criteri e limiti per le assunzioni di personale a tempo indeterminato per il triennio 2005-2007\", \"argument2\": [\"regioni\", \"province\", \"comuni\", \"unioni di comuni\", \"comunità montane\", \"consorzi\", \"Servizio Sanitario Nazionale\"]}, {\"role_name\": \"regulates\", \"argument1\": \"DPCM sui criteri e limiti per le assunzioni di personale a tempo indeterminato per il triennio 2005-2007\", \"argument2\": [\"contrazione delle dotazioni organiche\", \"fissazione dei criteri e dei limiti per le assunzioni a tempo indeterminato\"]}]}"}
{"instruction": "extract event trigger, the entities involved, and the roles that entities have in the event or the relationships between them. Output is in JSON format", "context": "L’ISVAP può chiedere alle imprese di assicurazione e di riassicurazione e alle società e agli enti di qualsiasi natura che possiedono partecipazioni nelle imprese medesime l'indicazione nominativa dei titolari delle partecipazioni secondo quanto risulta dal libro dei soci, dalle comunicazioni ricevute o da altri dati a loro disposizione. L'ISVAP può altresì richiedere agli amministratori delle società e degli enti titolari di partecipazioni in imprese di assicurazione e di riassicurazione l’indicazione dei soggetti controllanti. L'ISVAP, per la verifica di ogni interrelazione finanziaria con le società controllanti, controllate e collegate alle imprese di assicurazione e di riassicurazione, può chiedere informazioni, ordinare l'esibizione di documenti ed il compimento di accertamenti alle medesime società. Per gli accertamenti di cui ai commi 1, 2 e 3, l'ISVAP può chiedere informazioni ai soggetti, anche stranieri, titolari di una partecipazione in un'impresa di assicurazione o di riassicurazione.", "response": "{\"event_trigger\": [\"richiedere\", \"informa\"], \"legal_concepts\": [\"assetti proprietari\", \"indicazione nominativa delle partecipazioni\", \"interrelazione finanziaria\", \"società controllanti\", \"società controllate\", \"società collegate\", \"imprese di assicurazione\", \"imprese di riassicurazione\", \"amministratori\", \"soggetti controllanti\", \"informazioni\", \"documenti\", \"accertamenti\"], \"references\": null, \"actors\": [\"ISVAP\", \"imprese di assicurazione e di riassicurazione\", \"amministratori\"], \"keywords\": \"partecipazioni\", \"roles\": [{\"role_name\": \"agent\", \"argument1\": \"richiedere\", \"argument2\": \"ISVAP\"}, {\"role_name\": \"theme\", \"argument1\": \"richiedere\", \"argument2\": [\"indicazione nominativa delle partecipazioni\", \"soggetti controllanti\", \"informazioni\", \"documenti\", \"accertamenti\"]}, {\"role_name\": \"theme\", \"argument1\": \"richiedere\", \"argument2\": [\"indicazione nominativa delle partecipazioni\", \"soggetti controllanti\", \"informazioni\", \"documenti\", \"accertamenti\"]}, {\"role_name\": \"regulates\", \"argument1\": \"ISVAP\", \"argument2\": [\"società controllanti\", \"società controllate\", \"imprese di assicurazione\", \"imprese di riassicurazione\", \"amministratori\"]}]}"}
{"instruction": "extract event trigger and the entities involved in the event. Output is in JSON format", "context": "La Regione riconosce i Centri per la conservazione, la riproduzione, il recupero e il ricovero di specie animali e vegetali di interesse regionale e definisce, secondo quanto previsto dalla lettera e) del comma 1 dell'articolo 12, i requisiti strutturali degli stessi, nonché i requisiti organizzativi e strumentali il cui possesso deve essere accertato in capo ai soggetti interessati, anche ai fini dell'erogazione di eventuali finanziamenti. 2. I Centri di conservazione della fauna selvatica riconosciuti ai sensi del presente articolo possono essere riconosciuti anche quali Centri di recupero della fauna selvatica di cui all'articolo 38 della legge regionale 3/1994. Tali centri potranno altresì essere organizzati per la detenzione delle specie di cui è vietato il rilascio in natura ai sensi della legge 7 febbraio 1992, n. 150 e successive modificazioni e integrazioni, delle specie di cui al all'art. 5, comma 6, e di quelle sottoposte ad affidamento in custodia ai sensi dell'art.17, comma 8, della presente legge.", "response": "{\"event_trigger\": [\"riconosce\", \"potranno altresì essere organizzati\"], \"legal_concepts\": [\"Centri per la conservazione di specie animali e vegetali\", \"requisiti strutturali, organizzativi e strumentali\", \"Centri di recupero della fauna selvatica\", \"detenzione delle specie di cui è vietato il rilascio\"], \"references\": [\"lettera e del comma 1 dell'articolo 12\", \"articolo 38 della legge regionale 3/1994\", \"legge 7 febbraio 1992, n. 150\", \"art. 5, comma 6\", \"art.17, comma 8, della presente legge\"], \"actors\": \"Regione\", \"keywords\": \"erogazione di eventuali finanziamenti\"}"}
{"instruction": "extract event trigger and the roles that entities have in the event or the relationships between them. Output is in JSON format", "context": "La Regione riconosce i Centri per la conservazione, la riproduzione, il recupero e il ricovero di specie animali e vegetali di interesse regionale e definisce, secondo quanto previsto dalla lettera e) del comma 1 dell'articolo 12, i requisiti strutturali degli stessi, nonché i requisiti organizzativi e strumentali il cui possesso deve essere accertato in capo ai soggetti interessati, anche ai fini dell'erogazione di eventuali finanziamenti. 2. I Centri di conservazione della fauna selvatica riconosciuti ai sensi del presente articolo possono essere riconosciuti anche quali Centri di recupero della fauna selvatica di cui all'articolo 38 della legge regionale 3/1994. Tali centri potranno altresì essere organizzati per la detenzione delle specie di cui è vietato il rilascio in natura ai sensi della legge 7 febbraio 1992, n. 150.", "response": "{\"event_trigger\": [\"riconosce\", \"potranno altresì essere organizzati\"], \"roles\": [{\"role_name\": \"agent\", \"argument1\": \"riconosce\", \"argument2\": \"Regione\"}, {\"role_name\": \"theme\", \"argument1\": \"riconosce\", \"argument2\": [\"Centri per la conservazione\", \"Centri di recupero della fauna selvatica\"]}, {\"role_name\": \"regulates\", \"argument1\": \"lettera e del comma 1 dell'articolo 12\", \"argument2\": [\"Centri per la conservazione\", \"requisiti strutturali, organizzativi e strumentali\", \"erogazione di eventuali finanziamenti\"]}, {\"role_name\": \"regulates\", \"argument1\": \"lettera e del comma 1 dell'articolo 12\", \"argument2\": [\"Centri per la conservazione\", \"requisiti strutturali, organizzativi e strumentali\", \"erogazione di eventuali finanziamenti\"]}, {\"role_name\": \"agent\", \"argument1\": \"potranno altresì essere organizzati\", \"argument2\": \"Centri di recupero della fauna selvatica\"}, {\"role_name\": \"theme\", \"argument1\": \"potranno altresì essere organizzati\", \"argument2\": \"detenzione delle specie\"}, {\"role_name\": \"regulates\", \"argument1\": \"legge 7 febbraio 1992, n. 150\", \"argument2\": \"detenzione delle specie\"}]}"}
{"instruction": "extract event trigger, the entities involved, and the roles that entities have in the event or the relationships between them. Output is in JSON format", "context": "Peraltro, si dà atto dell'intervento di un membro supplente, non indicando i tre componenti, né si fa sua menzione dalla specificazione del membro effettivo sostituito.", "response": "{\"event_trigger\": \"si dà atto dell'intervento\", \"legal_concepts\": null, \"references\": null, \"actors\": [\"membro supplente\", \"membro effettivo sostituito\"], \"keywords\": null, \"roles\": [{\"role_name\": \"theme\", \"argument1\": \"si dà atto dell'intervento\", \"argument2\": \"un membro supplente\"}]}"}
{"instruction": "extract event trigger, the entities involved, and the roles that entities have in the event. Output is in JSON format", "context": "Ha cercato di ostacolare l'identificazione del responsabile di furto di occhiali da un negozio di ottica che dopo il furto è fuggito con il suo autocarro ed è stato denunciati per favoreggiamento personale. Nei guai è finito un 45enne residente a Modena denunciato dai carabinieri della stazione di Rubiera a conclusione di specifiche indagini relative al furto di occhiali asportati dall'interno di un negozio di ottica di Rubiera compiuto la mattina del 13 dicembre scorso. A carico dell'uomo risultato intestatario dell'autocarro Nissan Trade utilizzato dal malvivente per fuggire subito dopo il di furto, individuato dai militari, sono emersi concordanti elementi di colpevolezza tali da portare alla sua denuncia in stato di libertà inoltrata alla Procura reggiana in ordine al reato di favoreggiamento. Ad accorgersi del furto la mattina del 13 dicembre scorso lo stesso proprietario del negozio di ottica che aveva notato quello che riteneva essere un cliente impossessarsi di un paio d'occhiali da sole. Vistosi scoperto il ladro è uscito dal negozio balzando alla guida di un Nissan Trade a bordo del quale si dileguava. Le indagini dei carabinieri di Rubiera, a cui il derubato, ha formalizzato la denuncia, grazie anche alla targa fornita dal derubato che riusciva a rilevarla, hanno permesso di risalire all'autocarro utilizzata dal malvivente per allontanarsi dopo il compimento del furto. Il Nissan Trade è risultato essere intestata a una 45enne salernitano abitante a Modena su cui si sono indirizzate le attenzioni investigative dei carabinieri. È stato denunciato alla Procura reggiana per favoreggiamento personale.", "response": "{\"event_trigger\": \"furto\", \"author_of_theft\": null, \"victim_of_theft\": \"un negozio di ottica\", \"location\": \"un negozio di ottica di Rubiera\", \"object\": \"occhiali da sole\", \"temporal_expressions\": \"mattina del 13 dicembre scorso\", \"organizations\": \"carabinieri\"}"}
{"instruction": "extract event trigger, the entities involved, and the roles that entities have in the event. Output is in JSON format", "context": "Brutta sorpresa, all'alba di ieri, per i gestori del bar della Polisportiva San Faustino. Alcuni ladri, dopo aver rotto un vetro, hanno vuotato la cassa e sono riusciti a scappare non appena è suonato l'allarme. Sul posto sono arrivate le forze dell'ordine. La polisportiva, che si affaccia su via Wiligelmo e al suo interno ha diverse attività, è stata così presa di mira da malviventi che cercano incursioni notturne in spazi ricreativi, di quartiere o scolastici, che tanto in questi mesi sono statio presi di mira. Più del furto pesano però certamente i danni, dal momento che l'effrazione porterà a cambiare infissi e vetri per migliaia di euro.", "response": "{\"event_trigger\": \"hanno vuotato\", \"author_of_theft\": \"alcuni ladri\", \"victim_of_theft\": \"gestori del bar della Polisportiva San Faustino\", \"location\": \"la polisportiva, che si affaccia su via Wiligelmo\", \"object\": \"la cassa\", \"temporal_expressions\": \"all'alba di ieri\", \"organizations\": [\"la Polisportiva San Faustino\", \"carabinieri\"]}"}
{"instruction": "extract event trigger and the roles that entities have in the event or the relationships between them. Output is in JSON format", "context": "MODENA. A cinque anni dal clamoroso furto in San Vincenzo la tela del Guercino Madonna col Bambino e i santi Giovanni Evangelista e Gregorio Taumaturgo tornerà a Modena. Questa volta dopo aver adeguatamente predisposto misure di allarme e sicurezza, anche grazie al contributo della Fondazione Cassa di Risparmio. È quanto è stato spiegato ieri nel corso di una conferenza stampa in Procura in presenza del sindaco Gian Carlo Muzzarelli e del procuratore capo Lucia Musti, insieme al tenente colonnello Stefano Nencioni e al maggiore Giuseppe De Gori, comandante del Nucleo carabinieri tutela patrimonio culturale di Bologna. La tela, si ricorderà, fu rubata in un momento sconosciuto tra l'11 e il 14 agosto 2014 dalla chiesa di San Vincenzo. Dopo un lungo periodo di indagini infruttuose, emerse una verità sconcertante da Casablanca. La Procura della metropoli marocchina annunciò di aver arrestato alcuni ricettatori che avevano provato a venderla a un ricco collezionista di arte europea. Questi però aveva avvisato la polizia ed era scattata la trappola. In seguito, il pm Claudia Ferretti individuò il ladro della tela in Moustapha Tahir. Anche in questo caso emerse una verità sorprendente: Tahir abitava nello stesso palazzo comunicante con la chiesa, sul lato di via Gherarda. Tahir confessò, evitando l'estradizione in Marocco dove rischiava fino a vent'anni di carcere, e poche settimane fa ha chiuso la sua posizione con un patteggiamento di due anni, pena sospesa, e una multa.", "response": "{\"event trigger\": \"fu rubata\", \"author of the theft\": \"Moustapha Tahir\", \"victim of the theft\": \"chiesa di San Vincenzo\", \"location\": \"chiesa di San Vincenzo\", \"object\": \"tela del Guercino Madonna col Bambino e i santi Giovanni Evangelista e Gregorio Taumaturgo\", \"temporal expressions\": \"tra l'11 e il 14 agosto 2014\", \"organizations\": [\"Nucleo Tutela Patrimonio Artistico\", \"carabinieri\", \"Fondazione Cassa di Risparmio\"]}"}
{"instruction": "extract event trigger, the entities involved, and the roles that entities have in the event. Output is in JSON format", "context": "REGGIO EMILIA I carabinieri hanno recuperato 30 quintali di gasolio rubato dopo aver inseguito alcuni componenti della banda ribattezzata \"i vampiri del greggio\" dagli inquirenti. Si tratta di ladri specializzati nello svuotare i serbatoi di mezzi pesanti e aspirare il diesel contenente nelle cisterne di ditte o aziende agricole, per poi venderlo al mercato nero. accaduto stanotte a Guastalla, nella Bassa reggiana. L'allarme scattato intorno alle 2 quando una gazzella di militari ha intercettato un autocarro sospetto che si dato alla fuga. Cos nato un inseguimento a folle velocit lungo la Cispadana. I malviventi alla fine hanno accostato abbandonando il Fiat Daily - risultato rubato a Mirandola, nel modenese - per poi fuggire a piedi e a mani vuote. Gli uomini dell'Arma hanno cos perlustrato il camioncino, trovando varie taniche colme di gasolio rubato in un'azienda di Pegognaga, nel mantovano. Sui contenitori e sul furgone inoltre sono state prese le impronte digitali che verranno inviate ai Ris di Parma. In questo modo gli investigatori sperano di individuare i responsabili del colpo mancato.", "response": "{\"event_trigger\": \"rubato\", \"author_of_theft\": [\"banda\", \"i vampiri del greggio\"], \"victim_of_theft\": \"azienda di Pegognaga\", \"location\": \"Guastalla, nella Bassa reggiana\", \"object\": \"30 quintali di gasolio\", \"temporal_expressions\": \"accaduto stanotte\", \"organizations\": [\"carabinieri\", \"ditte o aziende agricole\", \"Ris di Parma\"]}"}
{"instruction": "extract event trigger, the entities involved, and the roles that entities have in the event. Output is in JSON format", "context": "Torna a far parlare di sé il villaggio artigianale di Spezzano, zona che negli ultimi mesi è stata protagonista di diversi episodi di criminalità, soprattutto furti di vario genere, specie alle attività commerciali. Ancora una volta a finire nel mirino dei ladri il Ristobar Capriccio, una nota attività della zona spezzanese che solo qualche mese fa era finita al centro della cronaca per un furto di gasolio. L'area infatti include non solo lo spazio di ristorazione ma anche la stazione di rifornimento, colpita nella scorsa triste vicenda che si è conclusa con notevoli ammanchi di carburante per il titolare Flavio Mazzucchi. Un gruppo di ignoti è riuscito ad introdursi verso le 2.30 di notte all'interno del locale sfondando la serranda con un'auto ariete rubata. Una volta dentro, hanno preso lo scambia soldi delle macchinette per poi fiondarsi anche sulla cassa. Ingenti i danni alla struttura: lo scenario che si sono trovati sotto agli occhi il titolare e i carabinieri era dei peggiori con la serranda sfondata, vetri rotti, soffitto danneggiato, vasi rovesciati, macchinette lasciate a terra, le porte finestre della veranda completamente da buttare, come i rottami di auto sparsi qua e là. È stata presentata regolare denuncia ai militari, che hanno avviato le indagini. Un disagio che continua anche in questi giorni visto che il bar non volendosi piegare alla criminalità ha già riaperto, ma tenendo l'entrata principale chiusa e facendo entrare i clienti da un ingresso secondario. La preoccupazione degli altri commercianti della zona cresce, così come l'esigenza di installare un sistema di videosorveglianza ai varchi d'ingresso per far in modo che la situazione non degeneri.", "response": "{\"event_trigger\": \"furti di vario genere\", \"author_of_theft\": \"gruppo di ignoti\", \"victim_of_theft\": [\"Ristobar Capriccio\", \"Flavio Mazzucchi\"], \"location\": \"interno del locale\", \"object\": \"scambia soldi delle macchinette\", \"temporal_expressions\": \"verso le 2.30 di notte\", \"organizations\": \"carabinieri\"}"}
{"instruction": "extract event trigger, the entities involved, and the roles that entities have in the event. Output is in JSON format", "context": "Non è sfuggito agli addetti alla sicurezza del centro commerciale che lo hanno bloccato consegnandolo ai carabinieri che lo hanno portato in caserma. Al centro di vicinato Torrenova, l'altra mattina, un 26enne ghanese era stato notato aggirarsi con fare sospetto tra gli scaffali dei prodotti. È stato pertanto tenuto d'occhio dal personale interno e quando ha superato la cassa e si è avviato verso l'uscita è stato fermato per un controllo. Sul posto nel frattempo è arrivato un equipaggio del Radiomobile dei carabinieri che ha perquisito il giovane: addosso aveva nascosti alcuni prodotti alimentari per 50 euro. Dopo gli accertamenti è stato denunciato per furto aggravato.", "response": "{\"event_trigger\": \"furto aggravato\", \"author_of_theft\": \"un 26enne ghanese\", \"victim_of_theft\": \"prodotti alimentari per 50 euro\", \"location\": \"centro commerciale di vicinato Torrenova\", \"temporal_expressions\": \"l'altra mattina\", \"organizations\": [\"personale interno\", \"Radiomobile dei carabinieri\"]}"}
{"instruction": "extract event trigger, the entities involved, and the roles that entities have in the event. Output is in JSON format", "context": "MODENA. Tentato furto ieri sera al Policlinico. Gli addetti alla vigilanza sono stati allertati ieri sera alle 19,50 dalla responsabile di una delle ditte in appalto del Policlinico che ha lo spogliatoio nel seminterrato della Palazzina di Malattie Infettive che aveva notato la presenza di un individuo sospetto che armeggiava negli armadietti e ne aveva forzato uno. Due vigilanti sono corsi sul posto e hanno intercettato un individuo sui quarant'anni che si stava dileguando con due borse e zoccoli sanitari. La Vigilanza ha fermato l'uomo, senza documenti, e gli ha ordinato di svuotare le borse, entrambe da donna. In una di queste borse hanno trovato i documenti di una dipendente della ditta in appalto. A questo punto è stata chiamata la dipendente insieme alla titolare della ditta che hanno riconosciuto la refurtiva. L'uomo ha quindi ammesso il furto, la Vigilanza nel frattempo aveva allertato i carabinieri che sono giunti sul posto e lo hanno arrestato. L'uomo è stato poi riconosciuto  grazie alle telecamere di sorveglianza - come un extracomunitario senza fissa dimora che era giunto in ambulanza per abuso etilico verso le 14,40 al Pronto soccorso e si era allontanato di sua spontanea volontà.", "response": "{\"event_trigger\": \"tentato furto\", \"author_of_the_theft\": \"un individuo sospetto\", \"victim_of_the_theft\": \"una delle ditte in appalto del Policlinico\", \"location\": \"Palazzina di Malattie Infettive\", \"object\": [\"due borse\", \"zoccoli sanitari\"], \"temporal_expressions\": \"ieri sera alle 19,50\", \"organizations\": [\"Policlinico\", \"Vigilanza\", \"Carabinieri\"]}"}
{"instruction": "extract event trigger, the entities involved, and the roles that entities have in the event. Output is in JSON format", "context": "PAVULLO. Ancora un tentativo di furto al supermercato Tigotà di Pavullo (alla Campanella), ancora fallito. È successo nei giorni scorsi, con protagonista una 50enne di origine romena, incensurata, che ha pensato bene di portarsi via un profumo. Ha tentato di farla franca infilandolo nella borsa dopo aver tolto l'etichetta, ma le commesse (che qui hanno l'occhio particolarmente allenato visti anche i ripetuti episodi dell'anno scorso) si sono accorte di tutto e l'hanno bloccata all'uscita, chiamando subito i carabinieri. E così la donna la dovuto lasciare lì il profumo portando a casa una denuncia per tentato furto aggravato dalla destrezza. A fine gennaio un altro tentativo di furto bloccato qui: un 65enne si è messo in guai grossi (contestata la rapina) per aver tentato di rubare un tagliaunghie.", "response": "{\"event_trigger\": \"tentato furto aggravato\", \"author_of_the_theft\": \"una 50enne di origine romena, incensurata\", \"victim_of_the_theft\": \"supermercato Tigotà di Pavullo\", \"location\": \"supermercato Tigotà di Pavullo (alla Campanella)\", \"object\": \"un profumo\", \"temporal_expressions\": \"nei giorni scorsi\", \"organizations\": \"carabinieri\"}"}
{"instruction": "extract event trigger, the entities involved, and the roles that entities have in the event. Output is in JSON format", "context": "Un'impiegata del liceo Pico di Mirandola è stata denunciata dai carabinieri della caserma cittadina per furto. La donna, classe '72, assistente amministrativa, è infatti stata riconosciuta come l'autrice materiale del furto di un giubbino di una studentessa avvenuto il 29 marzo.", "response": "{\"event_trigger\": \"furto\", \"author_of_theft\": \"un'impiegata del liceo Pico di Mirandola\", \"victim_of_theft\": \"una studentessa\", \"location\": \"liceo Pico di Mirandola\", \"object\": \"un giubbino\", \"temporal_expressions\": \"il 29 marzo\", \"organizations\": \"carabinieri della caserma cittadina\"}"}
{"instruction": "extract event trigger, the entities involved, and the roles that entities have in the event. Output is in JSON format", "context": "FINALE. Era l'8 febbraio quando, intorno all'ora di cena, i ladri arrivavano in via Selvabella e rubavano il Fiorino di Emanuele Lodi, conosciuto agricoltore finalese. Qualche giorno prima, sempre i ladri, avevano forzato catenaccio del magazzino e se n'erano andati con alcuni attrezzi per il giardino. Ma da quel giorno per Lodi è iniziata una lunga peripezia. Per prima cosa ha raggiunto la sua assicurazione per bloccare la polizza, che copriva il furgone per eventuali danni. Ha anche sperato di essere chiamato dalle forze dell'ordine per venire informato del ritrovamento del Fiorino 1300 bianco, targato DR806HP. Ma nulla di tutto ciò è avvenuto.. In compenso in via Selvabella hanno iniziato ad arrivare con puntualità alcune multe per eccesso di velocità. E a correre lungo le strade del distretto ceramico (tra Sassuolo, Fiorano e Modena) sono evidentemente i ladri che girano impuniti con ancora montata la targa originale del mezzo. «Vanno a velocità assurde - spiega Lodi - Le ultime due multe li hanno immortalati ad oltre 110 chilometri orari sulla Pedemontana di Fiorano e in tangenziale a Modena. Le sanzioni automatiche che mi vengono spedite dalla polizia municipale prevedono oltre 200 euro di spesa. È logico che non pagherò e farò ricorso, portando la denuncia di furto, ma quel Fiorino è pericoloso. Ricordo che è senza assicurazione e quindi se dovesse essere coinvolto in un incidente non ci sarebbe copertura. È soprattutto per questo che faccio un appello affinché lo intercetti possa comunicarlo subito ai carabinieri del proprio paese». Ma Lodi è anche tra gli agricoltori che si sono auto-organizzati in via Selvabella.", "response": "{\"event_trigger\": \"rubavano\", \"author_of_theft\": \"i ladri\", \"victim_of_theft\": \"Emanuele Lodi\", \"location\": \"via Selvabella\", \"object\": \"FiorFiorino 1300 bianco, targato DR806HP\", \"temporal_expressions\": \"8 febbraio\", \"organizations\": [\"assicurazione\", \"forze dell'ordine\", \"distretto ceramico\"]}"}
{"instruction": "extract event trigger, the entities involved, and the roles that entities have in the event. Output is in JSON format", "context": "SPILAMBERTO. Furto d'auto sabato sera, attorno alle 22, nei pressi di via Fratelli Rosselli. Alle 20.30 il proprietario della vettura rubata, un 40 enne di Crespellano, raggiunge come di consueto il suo amico a Spilamberto e lascia l'auto parcheggiata nella via: un'Alfa Romeo Giulietta. I due amici raggiunti poi da una terza persona si recano con un'altra auto a Modena per passare una serata in centro. Ma quando rientrano trovano brutta sorpresa: la Giulietta non c'è più. «È da 20 anni che vengo a Spilamberto e lascio la macchina nello stesso posto per poi andare a Modena - racconta il proprietario della vettura visibilmente incredulo - Non ci sono stati segni di infrazione come vetri rotti sparsi in giro... Semplicemente l'auto è stata rubata». Nella zona residenziale dove è accaduto il furto ci sono stati degli altri precedenti con i ladri che sono piombati in casa, in presenza dei proprietari. In quell'occasione uno dei malviventi fu rincorso dal figlio del proprietario ma quando il ladro ha estratto un coltello ha fatto desistere l'inseguitore che non voleva rischiare di essere ferito. Sulla strada non ci sono delle telecamere che riprendono il punto dove era parcheggiata l'auto ma a pochi metri ci sono delle abitazioni provviste di telecamere che potrebbero aver ripreso l'Alfa Romeo in fuga con i malviventi. Il caso è stato denunciato ai carabinieri.", "response": "{\"event trigger\": \"rubata\", \"author of the theft\": \"i  ladri\", \"victim of the theft\": \"40 enne di Crespellano\", \"location\": \"via Fratelli Rosselli\", \"object\": \"Alfa Romeo 'Giulietta\", \"temporal expressions\": [\"sabato sera\", \"alle 20.30\"], \"organizations\": \"carabinieri\"}"}
{"instruction": "extract event trigger, the entities involved, and the roles that entities have in the event. Output is in JSON format", "context": "Un 56enne modenese di origini torinesi con una lunga serie di condanne alle spalle per furti è stato arrestato l'altra sera alle 20.30 in corso Canalchiaro dagli agenti della Squadra volante di polizia subito dopo aver commesso un furto. Poco prima un residente di via dei Servi aveva sentito il rumore do un finestrino d'auto spaccato: era di una 500 rossa in sosta. Avvisata la polizia, il ladro è stato catturato in pochi minuti con tutta la refurtiva addosso (riconosciuta e riconsegnata alla proprietaria dell'auto danneggiata).", "response": "{\"event_trigger\": \"commesso un furto\", \"author_of_the_theft\": \"56enne modenese di origini torinesi\", \"victim_of_the_theft\": \"500 rossa\", \"location\": \"corso Canalchiaro\", \"object\": \"refurtiva\", \"temporal_expressions\": [\"sera 20.30\", \"poco prima\"], \"organizations\": \"polizia\"}"}
{"instruction": "extract event trigger, the entities involved, and the roles that entities have in the event. Output is in JSON format", "context": "AVARINO. Il tempo di presentare la denuncia del furto che i carabinieri hanno recuperato il maltolto, restituendolo all'89enne disperata e amareggiata per come era stata derubata, in modo pressoché beffardo. I militari infatti, grazie anche alle sommarie descrizioni che la stessa anziana aveva fornito del ladro, sono in pratica andati a botta sicura. Nella cittadina infatti questo 53enne è figura conosciuta, le sue gesta sono quelle riportate in un lungo curriculum di precedenti con la giustizia. Probabilmente il malvivente, abituato ad altre esperienze ladresche più impegnative, non aveva dato troppa importanza all'anziana, che lo aveva visto in azione e che lui aveva pure salutato nell'allontanarsi a bordo della vettura. Una spavalderia dimostrata anche dal fatto che l'auto, la Fiat 500 che aveva rubato all'anziana, non l'aveva nascosta chissà dove o abbandonata dopo un utilizzo, ma se l'era messa tranquillamente in garage. I carabinieri pertanto, che si erano recati a casa del 53enne per effettuare un doveroso controllo perché insospettiti dopo la denuncia dell'89enne, hanno avuto gioco facile, trovando, recuperando e restituendo la 500 all'anziana. La signora in fase di denuncia, aveva raccontato ai militari che si trovava in cortile quando ha visto passare un uomo che, con estrema nonchalance, ha aperto la portiera della sua 500 e ha messo in moto. Le chiavi erano all'interno della vettura proprio accanto a casa: il ladro ha salutato e se ne è andato. Ma, come è poi risultato, non è andato lontano. Il 53enne è stato denunciato.", "response": "{\"event_trigger\": \"furto\", \"author_of_theft\": \"53enne\", \"victim_of_theft\": \"89enne\", \"location\": [\"Ravarino\", \"garage\"], \"object\": \"Fiat 500\", \"temporal_expressions\": null, \"organizations\": \"carabinieri\"}"}
{"instruction": "extract event trigger, the entities involved, and the roles that entities have in the event. Output is in JSON format", "context": "PAVULLO. La domenica è giorno di messa e offerte, per una parte di popolazione. E di prelievo dalle cassettine appena riempite nelle chiese, per un'altra parte. Questo almeno è il sospetto che ha spinto i carabinieri della Compagnia di Pavullo, nell'ambito di un servizio di prevenzione furti, a fermare nel tardo pomeriggio di domenica a Sant'Antonio, su via Giardini Nord, la Punto con a bordo due individui che non hanno saputo spiegare perché si trovassero in possesso di una quantità considerevole di monete (per 130 euro circa, anche di piccolissimo taglio) nascoste un po' addosso e un po' nella macchina. Dappertutto insomma. Né come mai a corredo avessero anche un metro avvolgibile (come quello che i ladri usano per entrare nelle cassettine dalla fessura), di nastro adesivo (come quello utilizzato per fare attaccare le monete), di un cordino (come quello che serve per tirarle su) e di una piccola torcia (adattissima a guardare dentro quanta moneta c'è). Sono entrambi italiani e residenti nel reggiano: si tratta del 58enne F.P. e del 52enne F.C. Quest'ultimo, guarda caso, aveva precedenti proprio per furti nelle chiese. Sono stati denunciati per furto e possesso di oggetti atti allo scasso, che sono stati sequestrati al pari delle monete. In corso accertamenti per capire da quali chiese provengano e quando sono state prelevate: forse nella giornata stessa (contando sull'afflusso di fedeli) o da giorni in attesa di formare un gruzzoletto da scambiare in carta grazie a persone compiacenti (perché di per sé uno che arriva con tante monete qualche sospetto dovrebbe farlo venire). Non è escluso che i due abbiano prelevato anche banconote, riuscendo però a occultarle molto più facilmente.", "response": "{\"event_trigger\": \"hanno spinto i carabinieri a fermare\", \"author_of_theft\": [\"58enne F.P.\", \"52enne F.C.\", \"italiani e residenti nel reggiano\"], \"victim_of_theft\": \"chiese\", \"location\": \"chiese\", \"object\": \"monete per 130 euro circa\", \"temporal_expressions\": \"la domenica\", \"organizations\": \"carabinieri della Compagnia di Pavullo\"}"}
{"instruction": "extract event trigger, the entities involved, and the roles that entities have in the event. Output is in JSON format", "context": "PAVULLO. Non è passato inosservato alla gente di passaggio lo strano frugare in una Panda parcheggiata in via Rossini, a due passi dal centro, di un uomo che non aveva per niente l'aria di esserne il proprietario. E infatti all'arrivo dei carabinieri si è scoperto essere un aspirante ladro. È successo nella prima serata di domenica a Pavullo: i militari hanno sorpreso tutto indaffarato il 67enne S.M., di Napoli ma residente a Serramazzoni, pensionato con alle spalle qualche problema con la giustizia. Materialmente non aveva ancora portato via nulla, e va detto che la vecchia Panda l'aveva trovata aperta (non voleva portare via l'auto). Questo però non gli impedirà di rispondere del suo strano comportamento (l'anziano percepisce la pensione) con una denuncia per tentato furto.", "response": "{\"event_trigger\": \"tentato furto\", \"author_of_the_theft\": \"S.M., 67enne uomo di Napoli residente a Serramazzoni)\", \"victim_of_the_theft\": null, \"location\": \"via Rossini, centro di Pavullo\", \"object\": \"Panda\", \"temporal_expressions\": \"prima serata di domenica\", \"organizations\": \"Carabinieri\"}"}
{"instruction": "extract event trigger, the entities involved, and the roles that entities have in the event. Output is in JSON format", "context": "MODENA Hanno tamponato con la loro auto e spinto per diversi metri una vettura, poi sono usciti dal veicolo su cui viaggiavano e si sono allontanati in fretta a piedi, davanti a un'incredulità del conducente dell'altro mezzo coinvolto, che ha subito chiamato la Polizia municipale di Modena. Gli agenti, giunti in viale Vittorio Emanuele dove domenica 31 marzo verso le 21 si è verificato il sinistro, hanno subito capito i motivi di tale comportamento. L'auto abbandonata, un Opel Agila, presentava evidenti segni di scasso e, all'interno, erano in bella vista i cavi elettrici dell'accensione, utilizzati per metterla in moto senza le chiavi. Dagli accertamenti è infatti risultato che la vettura era stata rubata a Carpi una settimana prima e il furto regolarmente denunciato. Secondo il racconto dell'altro conducente, un romano in visita a Modena, l'Opel Agila sarebbe giunta a tutta velocità su viale Vittorio Veneto in direzione Accademia e avrebbe urtato violentemente la Fiat 500 intenta a spostarsi verso sinistra per parcheggiare, fortunatamente illeso il conducente. L'auto rubata è ora a disposizione della Polizia Scientifica per eventuali rilievi, poi sarà restituita al legittimo proprietario, mentre la Polizia Municipale ha acquisito le immagini della telecamera di videosorveglianza che potrebbe aver ripreso l'incidente per verificare elementi utili a risalire all'identità delle due persone che l'hanno abbandonata: un uomo di mezz'età che era alla guida e la passeggera, una ragazza più giovane.", "response": "{\"event_trigger\": \"era stata rubata\", \"author_of_theft\": [\"uomo di mezz'età\", \"ragazza più giovane\"], \"victim_of_theft\": \"legittimo proprietario\", \"location\": \"Carpi\", \"object\": \"l'auto, un Opel Agila\", \"temporal_expressions\": \"una settimana prima\", \"organizations\": [\"Polizia Scientifica\", \"Polizia Municipale\"]}"}
{"instruction": "extract event trigger, the entities involved, and the roles that entities have in the event. Output is in JSON format", "context": "Un furto in appartamento è stato messo a segno nella serata di ieri da ladri che molto probabilmente avevano a disposizione un flessibile per aprire cassaforti. Il colpo in via Santa Caterina, zona Crocetta, in un appartamento dove i ladri sono entrati cercando la cassaforte. Dopo averla individuata, sono riusciti a forzarla, presumibilmente utilizzando il cosiddetto flessibile adatto a questo tipo di operazioni. Hanno agito con notevole rapidità e sono riusciti a dileguarsi prima che i proprietari rientrassero trovando l'abitazione completamente sottosopra. Il bottino consiste prevalentemente di gioielli e preziosi che erano contenuti nella cassaforte, per un valore complessivo che, in base ai primi accertamenti, è stato stimato in circa 35mila euro. Sul posto è intervenuta la Polizia, che ha raccolto la denuncia delle vittime del furto.", "response": "{\"event_trigger\": \"furto\", \"author_of_theft\": \"ladri\", \"victim_of_theft\": \"i proprietari\", \"location\": \"via Santa Caterina, zona Crocetta\", \"object\": \"gioielli e preziosi\", \"temporal_expressions\": \"serata di ieri\", \"organizations\": \"Polizia\"}"}
{"instruction": "extract event trigger, the entities involved, and the roles that entities have in the event. Output is in JSON format", "context": "BOMPORTO. Sara e Giulia possono tirare un sospiro di sollievo: i loro abiti da sposa sono salvi, i ladri non hanno fatto in tempo a prenderseli e nel weekend andranno ai loro rispettivi matrimoni con indosso ciò che hanno sempre sognato. Ma è l'unica buona notizia di una notte in cui i ladri hanno fatto razzia al negozio Come nelle favole di Francesca Martinelli, in via per Modena. «Mi hanno portato via una decina di abiti da sposa, 1500 euro di bomboniere e hanno strappato la cassa», spiega la titolare mentre è ancora impegnata a sistemare il negozio dopo la spaccata notturna. Stando ad una prima ricostruzione i banditi sono entrati in azione intorno alla mezza. La pizzeria New Melody aveva appena chiuso quando è scattato l'allarme. «Il dubbio che stessero aspettando da qualche parte qui intorno è più che lecito», condivide Francesca. La banda è entrata nel piazzale, si è posizionata in retromarcia e a tutta velocità si è lanciata contro la vetrina, incurante che vi sia un muretto alto una ventina di centimetri a proteggerla proprio per contrastare le auto ariete. «Sono stati molto rapidi - spiega la titolare - Hanno preso quello che avevano a tiro, dagli abiti appena posizionati sui manichini alla cassa. Hanno distrutto i tavolini e seminato disastri un po' ovunque. Per fortuna, mi viene da dire, il vicino di casa è stato rapido ad affacciarsi e a costringerli a fuggire». Il gruppo è infatti risalito rapidamente sull'auto familiare scura e si è dileguato con direzione Modena. «Non so come siano ridotti gli abiti rubati - ammette Francesca - Mi raccontavano i testimoni che li vedevano penzolare dal baule e sfregare sull'asfalto mentre i ladri scappavano via». Un colpo dal valore di circa 13mila euro, ma che si aggiunge ad un periodo nerissimo per l'intero settore del wedding.", "response": "{\"event_trigger\": \"hanno portato via\", \"author_of_the_theft\": \"ladri\", \"victim_of_the_theft\": \"Francesca Martinelli\", \"location\": \"Come nelle favole di Francesca Martinelli, in via per Modena\", \"object\": \"una decina di abiti da sposa, 1500 euro di bomboniere, la cassa\", \"temporal_expressions\": \"intorno alla mezza\", \"organizations\": null}"}
{"instruction": "extract event trigger, the entities involved, and the roles that entities have in the event. Output is in JSON format", "context": "Sono pieghevoli proprio per essere trasportate ovunque in maniera pratica e agevole favorendo la mobilità sostenibile. Nella notte tra il 3 e il 4 luglio ad approfittare della versatilità delle due biciclette è stato però qualche delinquente che le ha rubate dal garage dell'abitazione di via Tiraboschi in cui erano custodite. Grazie alla segnalazione di un modenese, gli agenti della polizia locale hanno potuto però recuperare le bici pochi giorni dopo e non distante dal luogo del furto. Erano state abbandonate per trasportarle in un altro luogo o forse per la difficoltà a piazzare mezzi tanto particolari. Del modello rubato, del valore commerciale di 500 euro, a Modena sono state infatti venduti solo quattro esemplari: un elemento che ha reso più facile rintracciare il proprietario. Dal logo ancora presente sul telaio della bicicletta gli agenti della polizia locale del Centro Storico sono riusciti infatti a individuare il rivenditore e successivamente il proprietario delle due biciclette acquistate dalla stessa persona. Il rivenditore era in possesso non solo della descrizione e delle caratteristiche delle biciclette vendute, ma anche dei dati dell'acquirente. Il legittimo proprietario dei mezzi, un modenese 68enne residente in città, dopo aver sporto denuncia di furto presso l'Ufficio di Polizia giudiziaria del comando di via Galilei, venerdì mattina è stato convocato e ha avuto la bela notizia: è potuto rientrare in possesso delle sue biciclette.", "response": "{\"event_trigger\": \"rapina impropria\", \"author_of_theft\": \"nordafricano 40enne\", \"victim_of_theft\": \"operaio\", \"location\": \"azienda agricola\", \"object\": [\"borsello contenente il proprio telefono cellulare\", \"agnello\"], \"temporal_expressions\": \"11 luglio\", \"organizations\": \"carabinieri della stazione di Marano Sul Panaro\"}"}
{"instruction": "extract event trigger, the entities involved, and the roles that entities have in the event. Output is in JSON format", "context": "La corsa ciclistica, organizzata annualmente, attira partecipanti da tutto il paese.", "response": "{\"event_trigger\": \"attira\", \"events\": \"La corsa ciclistica\", \"people\": \"partecipanti\", \"roles\": [{\"role_name\": \"agent\", \"argument1\": \"attira\", \"argument2\": \"La corsa ciclistica\"}, {\"role_name\": \"theme\", \"argument1\": \"attira\", \"argument2\": \"partecipanti\"}, {\"role_name\": \"origin\", \"argument1\": \"partecipanti\", \"argument2\": \"tutto il paese\"}]}"}
{"instruction": "extract event trigger, the entities involved, and the roles that entities have in the event. Output is in JSON format", "context": "Dopo settimane di preparativi, la mostra fotografica ha finalmente aperto i battenti.", "response": "{\"event_trigger\": \"ha aperto\", \"events\": \"la mostra fotografica\", \"actions\": \"preparativi\", \"time_expressions\": \"settimane\", \"roles\": [{\"role_name\": \"agent\", \"argument1\": \"ha aperto\", \"argument2\": \"la mostra fotografica\"}, {\"role_name\": \"succeed\", \"argument1\": \"ha aperto\", \"argument2\": \"preparativi\"}, {\"role_name\": \"duration\", \"argument1\": \"settimane\", \"argument2\": \"preparativi\"}]}"}
{"instruction": "extract event trigger, the entities involved, and the roles that entities have in the event. Output is in JSON format", "context": "Un incontro improvviso tra diplomatici ha portato a discussioni cruciali per la pace.", "response": "{\"event_trigger\": \"ha portato\", \"events\": \"Un incontro improvviso\", \"people\": \"diplomatici\", \"actions\": \"discussioni\", \"roles\": [{\"role_name\": \"agent\", \"argument1\": \"ha portato\", \"argument2\": \"Un incontro improvviso\"}, {\"role_name\": \"theme\", \"argument1\": \"ha portato\", \"argument2\": \"discussioni\"}, {\"role_name\": \"result\", \"argument1\": \"discussioni\", \"argument2\": \"pace\"}]}"}
{"instruction": "extract event trigger, the entities involved, and the roles that entities have in the event. Output is in JSON format", "context": "La sperimentazione di un nuovo farmaco si è conclusa con risultati promettenti.", "response": "{\"event_trigger\": \"si è conclusa\", \"events\": \"sperimentazione di un nuovo farmaco\", \"objects\": \"nuovo farmaco\", \"concepts\": \"promettenti\", \"roles\": [{\"role_name\": \"agent\", \"argument1\": \"si è conclusa\", \"argument2\": \"sperimentazione\"}, {\"role_name\": \"theme\", \"argument1\": \"si è conclusa\", \"argument2\": \"nuovo farmaco\"}, {\"role_name\": \"result\", \"argument1\": \"promettenti\"}]}"}
{"instruction": "extract event trigger, the entities involved, and the roles that entities have in the event. Output is in JSON format", "context": "Durante il concerto rock, la folla ha vibrato al ritmo delle chitarre elettriche.", "response": "{\"event_trigger\": \"ha vibrato\", \"events\": \"concerto rock\", \"people\": \"folla\", \"objects\": \"chitarre elettriche\", \"concepts\": \"ritmo\", \"roles\": [{\"role_name\": \"agent\", \"argument1\": \"ha vibrato\", \"argument2\": \"la folla\"}, {\"role_name\": \"cause\", \"argument1\": \"ha vibrato\", \"argument2\": \"ritmo\"}]}"}
{"instruction": "extract event trigger, the entities involved, and the roles that entities have in the event. Output is in JSON format", "context": "La conferenza sulla sostenibilità ha riunito esperti da diverse discipline.", "response": "{\"event_trigger\": \"ha riunito\", \"events\": \"conferenza sulla sostenibilità\", \"people\": \"esperti\", \"roles\": [{\"role_name\": \"agent\", \"argument1\": \"ha riunito\", \"argument2\": \"La conferenza sulla sostenibilità\"}, {\"role_name\": \"theme\", \"argument1\": \"ha riunito\", \"argument2\": \"esperti\"}, {\"role_name\": \"origin\", \"argument1\": \"esperti\", \"argument2\": \"diverse discipline\"}]}"}
{"instruction": "extract event trigger, the entities involved, and the roles that entities have in the event. Output is in JSON format", "context": "Un incendio nella zona industriale ha richiesto l'intervento immediato dei pompieri.", "response": "{\"event_trigger\": \"ha richiesto\", \"events\": \"incendio\", \"people\": \"pompieri\", \"places\": \"zona industriale\", \"actions\": \"intervento\", \"roles\": [{\"role_name\": \"agent\", \"argument1\": \"ha richiesto\", \"argument2\": \"Un incendio\"}, {\"role_name\": \"theme\", \"argument1\": \"ha richiesto\", \"argument2\": \"intervento\"}, {\"role_name\": \"agent\", \"argument1\": \"intervento\", \"argument2\": \"pompieri\"}, {\"role_name\": \"location\", \"argument1\": \"zona industriale\", \"argument2\": \"incendio\"}]}"}
{"instruction": "extract event trigger, the entities involved, and the roles that entities have in the event. Output is in JSON format", "context": "Il lancio del libro dell'autore celebre ha attirato una vasta platea di lettori.", "response": "{\"event_trigger\": \"ha attirato\", \"events\": \"lancio del libro\", \"people\": [\"autore\", \"lettori\"], \"roles\": [{\"role_name\": \"agent\", \"argument1\": \"ha attirato\", \"argument2\": \"lancio del libro\"}, {\"role_name\": \"theme\", \"argument1\": \"ha attirato\", \"argument2\": \"lettori\"}]}"}
{"instruction": "extract event trigger, the entities involved, and the roles that entities have in the event. Output is in JSON format", "context": "Un flashmob sorpresa ha animato la piazza principale della città.", "response": "{\"event_trigger\": \"ha animato\", \"events\": \"flashmob sorpresa\", \"places\": \"piazza principale della città\", \"roles\": [{\"role_name\": \"agent\", \"argument1\": \"ha animato\", \"argument2\": \"Un flashmob sorpresa\"}, {\"role_name\": \"theme\", \"argument1\": \"ha animato\", \"argument2\": \"piazza principale della città\"}]}"}
{"instruction": "extract event trigger, the entities involved, and the roles that entities have in the event. Output is in JSON format", "context": "Una gara culinaria ha visto chef professionisti sfidarsi con piatti creativi.", "response": "{\"event_trigger\": \"ha visto\", \"events\": \"Una gara culinaria\", \"people\": \"chef professionisti\", \"actions\": \"sfidarsi\", \"roles\": [{\"role_name\": \"agent\", \"argument1\": \"ha visto\", \"argument2\": \"Una gara culinaria\"}, {\"role_name\": \"theme\", \"argument1\": \"ha visto\", \"argument2\": \"chef professionisti\"}, {\"role_name\": \"agent\", \"argument1\": \"sfidarsi\", \"argument2\": \"chef professionisti\"}]}"}
{"instruction": "extract event trigger, the entities involved, and the roles that entities have in the event. Output is in JSON format", "context": "Dopo mesi di intensa preparazione e pianificazione logistica, l'evento benefico annuale per la raccolta fondi ha finalmente preso il via, coinvolgendo centinaia di volontari e donatori provenienti da diverse parti del paese.", "response": "{\"event_trigger\": \"ha preso il via\", \"events\": \"evento benefico annuale\", \"people\": \"volontari e donatori\", \"actions\": [\"preparazione\", \"pianificazione\", \"raccolta fondi\"], \"places\": \"diverse parti del paese\", \"time_expressions\": \"mesi\", \"roles\": [{\"role_name\": \"agent\", \"argument1\": \"ha preso il via\", \"argument2\": \"evento benefico annuale\"}, {\"role_name\": \"theme\", \"argument1\": \"ha preso il via\", \"argument2\": \"volontari e donatori\"}, {\"role_name\": \"goal\", \"argument1\": \"evento benefico annuale\", \"argument2\": \"raccola fondi\"}, {\"role_name\": \"succeed\", \"argument1\": \"ha preso il via\", \"argument2\": [\"preparazione\", \"pianificazione\"]}, {\"role_name\": \"duration\", \"argument1\": \"mesi\", \"argument2\": [\"preparazione\", \"pianificazione\"]}, {\"role_name\": \"origin\", \"argument1\": \"volontari e donatori\", \"argument2\": \"diverse parti del paese\"}]}"}
{"instruction": "extract event trigger, the entities involved, and the roles that entities have in the event. Output is in JSON format", "context": "La realizzazione del progetto di riqualificazione urbana, iniziativa ambiziosa del comune, ha coinvolto urbanisti, architetti e residenti in un processo partecipativo durato oltre un anno.", "response": "{\"event_trigger\": \"ha coinvolto\", \"events\": \"progetto di riqualificazione urbana\", \"people\": [\"urbanisti\", \"architetti\", \"residenti\"], \"actions\": \"realizzazione\", \"concepts\": [\"iniziativa ambiziosa\", \"processo partecipativo\"], \"time_expressions\": \"un anno\", \"roles\": [{\"role_name\": \"agent\", \"argument1\": \"ha coinvolto\", \"argument2\": \"progetto di riqualificazione urbana\"}, {\"role_name\": \"theme\", \"argument1\": \"ha coinvolto\", \"argument2\": [\"urbanisti\", \"architetti\", \"residenti\"]}, {\"role_name\": \"duration\", \"argument1\": \"un anno\", \"argument2\": \"progetto di riqualificazione urbana\"}]}"}
{"instruction": "extract event trigger, the entities involved, and the roles that entities have in the event. Output is in JSON format", "context": "Un'accademia di formazione professionale ha organizzato un corso di aggiornamento per gli insegnanti delle scuole medie, focalizzato su nuove metodologie didattiche e approcci innovativi all'educazione.", "response": "{\"event_trigger\": \"ha organizzato\", \"events\": \"corso di aggiornamento\", \"organizations\": \"accademia di formazione\", \"people\": \"insegnanti delle scuole medie\", \"actions\": \"formazione\", \"concepts\": [\"nuove metodologie didattiche\", \"approcci innovativi\"], \"roles\": [{\"role_name\": \"agent\", \"argument1\": \"ha organizzato\", \"argument2\": \"accademia di formazione\"}, {\"role_name\": \"theme\", \"argument1\": \"ha organizzato\", \"argument2\": \"corso di aggiornamento\"}, {\"role_name\": \"goal\", \"argument1\": \"corso di aggiornamento\", \"argument2\": [\"nuove metodologie didattiche\", \"approcci innovativi\"]}]}"}
{"instruction": "extract event trigger, the entities involved, and the roles that entities have in the event. Output is in JSON format", "context": "Il festival musicale, giunto alla sua decima edizione, ha presentato un ricco cartellone artistico, accogliendo musicisti internazionali e appassionati provenienti da ogni angolo del globo.", "response": "{\"event_trigger\": \"ha presentato\", \"events\": \"festival musicale\", \"people\": [\"musicisti internazionali\", \"appassionati\"], \"concepts\": \"cartellone artistico\", \"roles\": [{\"role_name\": \"agent\", \"argument1\": \"ha presentato\", \"argument2\": \"festival musicale\"}, {\"role_name\": \"theme\", \"argument1\": \"ha presentato\", \"argument2\": \"musicisti internazionali e appassionati\"}]}"}
{"instruction": "extract event trigger, the entities involved, and the roles that entities have in the event. Output is in JSON format", "context": "Un incidente stradale in una delle arterie principali della città ha richiesto l'intervento tempestivo delle forze dell'ordine e dei soccorsi, causando disagi al traffico per diverse ore.", "response": "{\"event_trigger\": \"ha richiesto l'intervento\", \"events\": \"incidente stradale\", \"people\": [\"forze dell'ordine\", \"soccorsi\"], \"places\": \"una delle arterie principali della città\", \"concepts\": \"disagi al traffico\", \"roles\": [{\"role_name\": \"agent\", \"argument1\": \"ha richiesto l'intervento\", \"argument2\": \"incidente stradale\"}, {\"role_name\": \"theme\", \"argument1\": \"ha richiesto\", \"argument2\": [\"forze dell'ordine\", \"soccorsi\"]}, {\"role_name\": \"location\", \"argument1\": \"incidente stradale\", \"argument2\": \"una delle arterie principali della città\"}]}"}
{"instruction": "extract event trigger, the entities involved, and the roles that entities have in the event. Output is in JSON format", "context": "La commemorazione del centenario della fondazione dell'associazione culturale ha visto la partecipazione di illustri ospiti, con discorsi accattivanti e proiezioni storiche che hanno suscitato emozioni e ricordi.", "response": "{\"event_trigger\": [\"ha visto\", \"suscitato\"], \"events\": \"commemorazione del centenario\", \"people\": \"illustri ospiti\", \"actions\": [\"discorsi\", \"proiezioni\"], \"concepts\": [\"emozioni\", \"ricordi\"], \"roles\": [{\"role_name\": \"theme\", \"argument1\": \"ha visto la partecipazione\", \"argument2\": \"commemorazione del centenario\"}, {\"role_name\": \"agent\", \"argument1\": \"ha visto la partecipazione\", \"argument2\": \"illustri ospiti\"}, {\"role_name\": \"theme\", \"argument1\": \"suscitato\", \"argument2\": [\"emozioni\", \"ricordi\"]}, {\"role_name\": \"agent\", \"argument1\": \"suscitato\", \"argument2\": [\"discorsi\", \"proiezioni\"]}]}"}
{"instruction": "extract event trigger, the entities involved, and the roles that entities have in the event. Output is in JSON format", "context": "Un'escursione naturalistica organizzata da un gruppo di appassionati di birdwatching ha permesso agli amanti della natura di avvistare rare specie di uccelli lungo un sentiero panoramico.", "response": "{\"event_trigger\": \"ha permesso di avvistare\", \"events\": \"escursione naturalistica\", \"people\": [\"amanti della natura\", \"appassionati di birdwatching\"], \"objects\": [\"rare specie di uccelli\", \"sentiero panoramico\"], \"roles\": [{\"role_name\": \"agent\", \"argument1\": \"ha permesso di avvistare\", \"argument2\": \"escursione naturalistica\"}, {\"role_name\": \"theme\", \"argument1\": \"ha permesso di avvistare\", \"argument2\": \"rare specie di uccelli\"}, {\"role_name\": \"location\", \"argument1\": \"ha permesso di avvistare\", \"argument2\": \"sentiero panoramico\"}]}"}
{"instruction": "extract event trigger, the entities involved, and the roles that entities have in the event. Output is in JSON format", "context": "La presentazione del nuovo prodotto tecnologico da parte di un'azienda leader nel settore ha attirato l'attenzione di giornalisti, esperti del settore e curiosi desiderosi di scoprire le ultime innovazioni.", "response": "{\"event_trigger\": \"ha attirato\", \"events\": \"presentazione del nuovo prodotto tecnologico\", \"people\": [\"giornalisti\", \"esperti\", \"curiosi\"], \"organizations\": \"azienda leader del settore\", \"actions\": \"scoprire\", \"concepts\": \"ultime innovazioni\", \"roles\": [{\"role_name\": \"agent\", \"argument1\": \"ha attirato\", \"argument2\": \"presentazione del nuovo prodotto tecnologico\"}, {\"role_name\": \"theme\", \"argument1\": \"ha attirato\", \"argument2\": [\"giornalisti\", \"esperti\", \"curiosi\"]}, {\"role_name\": \"cause\", \"argument1\": \"ultime innovazioni\", \"argument2\": \"ha attirato\"}]}"}
{"instruction": "extract event trigger, the entities involved, and the roles that entities have in the event. Output is in JSON format", "context": "Un workshop intensivo di sviluppo personale, condotto da esperti nel campo del benessere mentale, ha offerto ai partecipanti strumenti pratici per gestire lo stress e migliorare la qualità della vita.", "response": "{\"event_trigger\": \"ha offerto\", \"events\": \"workshop intensivo di sviluppo personale\", \"people\": \"partecipanti\", \"actions\": [\"gestione dello stress\", \"miglioramento della qualità della vita\"], \"concepts\": [\"strumenti pratici\", \"benessere mentale\"], \"roles\": [{\"role_name\": \"agent\", \"argument1\": \"ha offerto\", \"argument2\": \"workshop intensivo di sviluppo personale\"}, {\"role_name\": \"theme\", \"argument1\": \"ha offerto\", \"argument2\": [\"strumenti pratici\", \"benessere mentale\"]}, {\"role_name\": \"goal\", \"argument1\": [\"strumenti pratici\", \"benessere mentale\"], \"argument2\": [\"gestione dello stress\", \"miglioramento della qualità della vita\"]}]}"}
