{"instruction": "extract event trigger, the entities involved, and the roles that entities have in the event. Output is in JSON format", "context": "Durante il concerto rock, la folla ha vibrato al ritmo delle chitarre elettriche.", "response": "{\"event_trigger\": \"ha vibrato\", \"events\": \"concerto rock\", \"people\": \"folla\", \"objects\": \"chitarre elettriche\", \"concepts\": \"ritmo\", \"roles\": [{\"role_name\": \"agent\", \"argument1\": \"ha vibrato\", \"argument2\": \"la folla\"}, {\"role_name\": \"cause\", \"argument1\": \"ha vibrato\", \"argument2\": \"ritmo\"}]}"}
{"instruction": "extract event trigger, the entities involved, and the roles that entities have in the event. Output is in JSON format", "context": "BOMPORTO. Sara e Giulia possono tirare un sospiro di sollievo: i loro abiti da sposa sono salvi, i ladri non hanno fatto in tempo a prenderseli e nel weekend andranno ai loro rispettivi matrimoni con indosso ciò che hanno sempre sognato. Ma è l'unica buona notizia di una notte in cui i ladri hanno fatto razzia al negozio Come nelle favole di Francesca Martinelli, in via per Modena. «Mi hanno portato via una decina di abiti da sposa, 1500 euro di bomboniere e hanno strappato la cassa», spiega la titolare mentre è ancora impegnata a sistemare il negozio dopo la spaccata notturna. Stando ad una prima ricostruzione i banditi sono entrati in azione intorno alla mezza. La pizzeria New Melody aveva appena chiuso quando è scattato l'allarme. «Il dubbio che stessero aspettando da qualche parte qui intorno è più che lecito», condivide Francesca. La banda è entrata nel piazzale, si è posizionata in retromarcia e a tutta velocità si è lanciata contro la vetrina, incurante che vi sia un muretto alto una ventina di centimetri a proteggerla proprio per contrastare le auto ariete. «Sono stati molto rapidi - spiega la titolare - Hanno preso quello che avevano a tiro, dagli abiti appena posizionati sui manichini alla cassa. Hanno distrutto i tavolini e seminato disastri un po' ovunque. Per fortuna, mi viene da dire, il vicino di casa è stato rapido ad affacciarsi e a costringerli a fuggire». Il gruppo è infatti risalito rapidamente sull'auto familiare scura e si è dileguato con direzione Modena. «Non so come siano ridotti gli abiti rubati - ammette Francesca - Mi raccontavano i testimoni che li vedevano penzolare dal baule e sfregare sull'asfalto mentre i ladri scappavano via». Un colpo dal valore di circa 13mila euro, ma che si aggiunge ad un periodo nerissimo per l'intero settore del wedding.", "response": "{\"event_trigger\": \"hanno portato via\", \"author_of_the_theft\": \"ladri\", \"victim_of_the_theft\": \"Francesca Martinelli\", \"location\": \"Come nelle favole di Francesca Martinelli, in via per Modena\", \"object\": \"una decina di abiti da sposa, 1500 euro di bomboniere, la cassa\", \"temporal_expressions\": \"intorno alla mezza\", \"organizations\": null}"}
{"instruction": "extract event trigger, the entities involved, and the roles that entities have in the event. Output is in JSON format", "context": "Un'accademia di formazione professionale ha organizzato un corso di aggiornamento per gli insegnanti delle scuole medie, focalizzato su nuove metodologie didattiche e approcci innovativi all'educazione.", "response": "{\"event_trigger\": \"ha organizzato\", \"events\": \"corso di aggiornamento\", \"organizations\": \"accademia di formazione\", \"people\": \"insegnanti delle scuole medie\", \"actions\": \"formazione\", \"concepts\": [\"nuove metodologie didattiche\", \"approcci innovativi\"], \"roles\": [{\"role_name\": \"agent\", \"argument1\": \"ha organizzato\", \"argument2\": \"accademia di formazione\"}, {\"role_name\": \"theme\", \"argument1\": \"ha organizzato\", \"argument2\": \"corso di aggiornamento\"}, {\"role_name\": \"goal\", \"argument1\": \"corso di aggiornamento\", \"argument2\": [\"nuove metodologie didattiche\", \"approcci innovativi\"]}]}"}
{"instruction": "extract event trigger, the entities involved, and the roles that entities have in the event or the relationships between them. Output is in JSON format", "context": "Con riguardo a quest'ultimo parametro, ossia l'affidamento diretto del servizio, s'è condivisibilmente affermato (cfr., approfonditamente sul punto, Cons. St., ad. plen.", "response": "{\"event_trigger\": \"s'è condivisibilmente affermato\", \"legal_concepts\": \"affidamento diretto del servizio\", \"references\": \"Cons. St., ad. plen.\", \"actors\": null, \"keywords\": null, \"roles\": null}"}
{"instruction": "extract event trigger, the entities involved, and the roles that entities have in the event. Output is in JSON format", "context": "Sono pieghevoli proprio per essere trasportate ovunque in maniera pratica e agevole favorendo la mobilità sostenibile. Nella notte tra il 3 e il 4 luglio ad approfittare della versatilità delle due biciclette è stato però qualche delinquente che le ha rubate dal garage dell'abitazione di via Tiraboschi in cui erano custodite. Grazie alla segnalazione di un modenese, gli agenti della polizia locale hanno potuto però recuperare le bici pochi giorni dopo e non distante dal luogo del furto. Erano state abbandonate per trasportarle in un altro luogo o forse per la difficoltà a piazzare mezzi tanto particolari. Del modello rubato, del valore commerciale di 500 euro, a Modena sono state infatti venduti solo quattro esemplari: un elemento che ha reso più facile rintracciare il proprietario. Dal logo ancora presente sul telaio della bicicletta gli agenti della polizia locale del Centro Storico sono riusciti infatti a individuare il rivenditore e successivamente il proprietario delle due biciclette acquistate dalla stessa persona. Il rivenditore era in possesso non solo della descrizione e delle caratteristiche delle biciclette vendute, ma anche dei dati dell'acquirente. Il legittimo proprietario dei mezzi, un modenese 68enne residente in città, dopo aver sporto denuncia di furto presso l'Ufficio di Polizia giudiziaria del comando di via Galilei, venerdì mattina è stato convocato e ha avuto la bela notizia: è potuto rientrare in possesso delle sue biciclette.", "response": "{\"event_trigger\": \"rapina impropria\", \"author_of_theft\": \"nordafricano 40enne\", \"victim_of_theft\": \"operaio\", \"location\": \"azienda agricola\", \"object\": [\"borsello contenente il proprio telefono cellulare\", \"agnello\"], \"temporal_expressions\": \"11 luglio\", \"organizations\": \"carabinieri della stazione di Marano Sul Panaro\"}"}
{"instruction": "extract event trigger, the entities involved, and the roles that entities have in the event or the relationships between them. Output is in JSON format", "context": "Proprio in materia di “controllo analogo”, i giudici di Palazzo Spada, dopo aver diligentemente elencato tutti gli arresti della Corte di giustizia intervenuti sull’argomento, a cominciare dalla sentenza “Stadt Halle” dell’11 gennaio 2005, hanno confermato che non può sussistere il requisito in parola in quei casi in cui si dia vita ad un modulo societario misto, ancorché a partecipazione privata estremamente ridotta.", "response": "{\"event_trigger\": \"hanno confermato che non può sussistere\", \"legal_concepts\": [\"controllo analogo\", \"requisito in parola\", \"modulo societario misto\", \"partecipazione privata\"], \"references\": \"sentenza Stadt Halle dell'11 gennaio 2005\", \"actors\": [\"giudici di Palazzo Spada\", \"Corte di giustizia\"], \"keywords\": [\"arresti\", \"modulo societario misto\", \"partecipazione privata estremamente ridotta\"], \"roles\": [{\"role_name\": \"agent\", \"argument1\": \"hanno confermato che non può sussistere\", \"argument2\": \"giudici di Palazzo Spada\"}, {\"role_name\": \"theme\", \"argument1\": \"hanno confermato che non può sussistere\", \"argument2\": \"requisito in parola\"}, {\"role_name\": \"regulates\", \"argument1\": \"modulo societario misto\", \"argument2\": \"requisito in parola\"}]}"}
{"instruction": "extract event trigger, the entities involved, and the roles that entities have in the event. Output is in JSON format", "context": "Un'escursione naturalistica organizzata da un gruppo di appassionati di birdwatching ha permesso agli amanti della natura di avvistare rare specie di uccelli lungo un sentiero panoramico.", "response": "{\"event_trigger\": \"ha permesso di avvistare\", \"events\": \"escursione naturalistica\", \"people\": [\"amanti della natura\", \"appassionati di birdwatching\"], \"objects\": [\"rare specie di uccelli\", \"sentiero panoramico\"], \"roles\": [{\"role_name\": \"agent\", \"argument1\": \"ha permesso di avvistare\", \"argument2\": \"escursione naturalistica\"}, {\"role_name\": \"theme\", \"argument1\": \"ha permesso di avvistare\", \"argument2\": \"rare specie di uccelli\"}, {\"role_name\": \"location\", \"argument1\": \"ha permesso di avvistare\", \"argument2\": \"sentiero panoramico\"}]}"}
{"instruction": "extract event trigger, the entities involved, and the roles that entities have in the event or the relationships between them. Output is in JSON format", "context": "I centri residenziali studenteschi devono essere progettati con la predisposizione di almeno 100 posti letto, con saloni per riunioni, assemblee e convegni, e sale biblioteca e studio, impianti sportivi e refettorio con una capacità di servizi per almeno 200 persone. Alla consegna, le opere passano in proprietà dei Comuni con destinazione di cui al presente regolamento e con i conseguenti oneri di manutenzione.", "response": "{\"event_trigger\": [\"devono essere progettati con la predisposizione\", \"passano in proprietà\"], \"legal_concepts\": [\"centri residenziali studenteschi\", \"proprietà\", \"destinazione\", \"oneri di manutenzione\"], \"references\": null, \"actors\": \"Comuni\", \"keywords\": [\"posti letto\", \"saloni per riunioni, assemblee e convegni\", \"sale biblioteca e studio\", \"impianti sportivi\", \"refettorio\", \"capacità di servizi\", \"opere\"], \"roles\": [{\"role_name\": \"agent\", \"argument2\": \"devono essere progettati con la predisposizione\", \"argument1\": \"centri residenziali studenteschi\"}, {\"role_name\": \"theme\", \"argument2\": \"devono essere progettati con la predisposizione\", \"argument1\": [\"posti letto\", \"saloni per riunioni, assemblee e convegni\", \"sale biblioteca e studio\", \"impianti sportivi\", \"refettorio\", \"capacità di servizi\"]}, {\"role_name\": \"agent\", \"argument2\": \"passano in proprietà\", \"argument1\": \"Comuni\"}, {\"role_name\": \"theme\", \"argument1\": \"passano in proprietà\", \"argument2\": \"opere\"}]}"}
{"instruction": "extract event trigger, the entities involved, and the roles that entities have in the event. Output is in JSON format", "context": "Ha cercato di ostacolare l'identificazione del responsabile di furto di occhiali da un negozio di ottica che dopo il furto è fuggito con il suo autocarro ed è stato denunciati per favoreggiamento personale. Nei guai è finito un 45enne residente a Modena denunciato dai carabinieri della stazione di Rubiera a conclusione di specifiche indagini relative al furto di occhiali asportati dall'interno di un negozio di ottica di Rubiera compiuto la mattina del 13 dicembre scorso. A carico dell'uomo risultato intestatario dell'autocarro Nissan Trade utilizzato dal malvivente per fuggire subito dopo il di furto, individuato dai militari, sono emersi concordanti elementi di colpevolezza tali da portare alla sua denuncia in stato di libertà inoltrata alla Procura reggiana in ordine al reato di favoreggiamento. Ad accorgersi del furto la mattina del 13 dicembre scorso lo stesso proprietario del negozio di ottica che aveva notato quello che riteneva essere un cliente impossessarsi di un paio d'occhiali da sole. Vistosi scoperto il ladro è uscito dal negozio balzando alla guida di un Nissan Trade a bordo del quale si dileguava. Le indagini dei carabinieri di Rubiera, a cui il derubato, ha formalizzato la denuncia, grazie anche alla targa fornita dal derubato che riusciva a rilevarla, hanno permesso di risalire all'autocarro utilizzata dal malvivente per allontanarsi dopo il compimento del furto. Il Nissan Trade è risultato essere intestata a una 45enne salernitano abitante a Modena su cui si sono indirizzate le attenzioni investigative dei carabinieri. È stato denunciato alla Procura reggiana per favoreggiamento personale.", "response": "{\"event_trigger\": \"furto\", \"author_of_theft\": null, \"victim_of_theft\": \"un negozio di ottica\", \"location\": \"un negozio di ottica di Rubiera\", \"object\": \"occhiali da sole\", \"temporal_expressions\": \"mattina del 13 dicembre scorso\", \"organizations\": \"carabinieri\"}"}
{"instruction": "extract event trigger, the entities involved, and the roles that entities have in the event or the relationships between them. Output is in JSON format", "context": "La deliberazione parlamentare di bilancio, basata sulle UPB, viene ad essere variata attraverso atti amministrativi, che finiscono per alterare significativamente il piano finanziario di inizio d’anno.", "response": "{\"event_trigger\": [\"viene ad essere variata\", \"alterare\"], \"legal_concepts\": [\"deliberazione parlamentare di bilancio\", \"atti amministrativi\", \"UPB\", \"piano finanziario\"], \"references\": null, \"actors\": null, \"keywords\": null, \"roles\": [{\"role_name\": \"agent\", \"argument1\": \"viene ad essere variata\", \"argument2\": \"atti amministrativi\"}, {\"role_name\": \"theme\", \"argument1\": \"viene ad essere variata\", \"argument2\": \"deliberazione parlamentare di bilancio\"}, {\"role_name\": \"agent\", \"argument1\": \"alterare\", \"argument2\": \"atti amministrativi\"}, {\"role_name\": \"theme\", \"argument1\": \"alterare\", \"argument2\": \"piano finanziario\"}, {\"role_name\": \"regulates\", \"argument1\": \"UPB\", \"argument2\": \"deliberazione parlamentare di bilancio\"}]}"}
{"instruction": "extract event trigger, the entities involved, and the roles that entities have in the event. Output is in JSON format", "context": "SPILAMBERTO. Furto d'auto sabato sera, attorno alle 22, nei pressi di via Fratelli Rosselli. Alle 20.30 il proprietario della vettura rubata, un 40 enne di Crespellano, raggiunge come di consueto il suo amico a Spilamberto e lascia l'auto parcheggiata nella via: un'Alfa Romeo Giulietta. I due amici raggiunti poi da una terza persona si recano con un'altra auto a Modena per passare una serata in centro. Ma quando rientrano trovano brutta sorpresa: la Giulietta non c'è più. «È da 20 anni che vengo a Spilamberto e lascio la macchina nello stesso posto per poi andare a Modena - racconta il proprietario della vettura visibilmente incredulo - Non ci sono stati segni di infrazione come vetri rotti sparsi in giro... Semplicemente l'auto è stata rubata». Nella zona residenziale dove è accaduto il furto ci sono stati degli altri precedenti con i ladri che sono piombati in casa, in presenza dei proprietari. In quell'occasione uno dei malviventi fu rincorso dal figlio del proprietario ma quando il ladro ha estratto un coltello ha fatto desistere l'inseguitore che non voleva rischiare di essere ferito. Sulla strada non ci sono delle telecamere che riprendono il punto dove era parcheggiata l'auto ma a pochi metri ci sono delle abitazioni provviste di telecamere che potrebbero aver ripreso l'Alfa Romeo in fuga con i malviventi. Il caso è stato denunciato ai carabinieri.", "response": "{\"event trigger\": \"rubata\", \"author of the theft\": \"i  ladri\", \"victim of the theft\": \"40 enne di Crespellano\", \"location\": \"via Fratelli Rosselli\", \"object\": \"Alfa Romeo 'Giulietta\", \"temporal expressions\": [\"sabato sera\", \"alle 20.30\"], \"organizations\": \"carabinieri\"}"}
{"instruction": "extract event trigger and the entities involved in the event. Output is in JSON format", "context": "Finalmente è stato raggiunto in sede di Conferenza Unificata lo scorso 24 novembre il fatidico accordo necessario per l’emanazione dei tanto attesi DPCM sui criteri e limiti per le assunzioni di personale a tempo indeterminato per il triennio 2005-2007. Perché la situazione si sblocchi definitivamente è ancora necessaria l’emanazione del vero e proprio Decreto del Presidente del Consiglio dei Ministri e la relativa pubblicazione sulla Gazzetta Ufficiale, per cui l’iter probabilmente si concluderà tra la fine di dicembre e gli inizi di gennaio. In ogni caso l’accordo è raggiunto e, fortunatamente, non si limita al 2005, estendendo la sua validità anche ai prossimi due anni, cosa questa di non poco conto se si considera il ritardo con il quale questo DPCM sarà reso noto. Come disciplinato in Finanziaria, l’accordo riguarda sia la contrazione delle dotazioni organiche che la fissazione dei criteri e dei limiti per le assunzioni a tempo indeterminato e si rivolge a regioni, province, comuni, unioni di comuni, comunità montane e consorzi, oltre agli enti del Servizio Sanitario Nazionale.", "response": "{\"event_trigger\": \"emanazione\", \"legal_concepts\": [\"contrazione delle dotazioni organiche\", \"fissazione dei criteri e dei limiti per le assunzioni a tempo indeterminato\", \"regioni\", \"province\", \"comuni\", \"unioni di comuni\", \"comunità montane\", \"consorzi\", \"Servizio Sanitario Nazionale\", \"Finanziaria\", \"tetto di spesa complessivo\"], \"references\": \"DPCM sui criteri e limiti per le assunzioni di personale a tempo indeterminato per il triennio 2005-2007\", \"actors\": [\"regioni\", \"province\", \"comuni\", \"unioni di comuni\", \"comunità montane\", \"consorzi\", \"Presidente del Consiglio dei Ministri\"], \"keywords\": [\"Conferenza Unificata\", \"Gazzetta Ufficiale\"]}"}
{"instruction": "extract event trigger, the entities involved, and the roles that entities have in the event or the relationships between them. Output is in JSON format", "context": "TABELLA Legenda: UP: Ufficio periferico UCCE: Ufficio di coordinamento e controllo dighe in esercizio UCPL: Ufficio di coordinamento e controllo vigilanza lavori UCSR: Ufficio di coordinamento Studi e Ricerche.", "response": "{\"event_trigger\": null, \"legal_concepts\": null, \"references\": null, \"actors\": [\"UP\", \"UCCE\", \"UCPL\", \"UCSR\", \"Ufficio periferico\", \"Ufficio di coordinamento e controllo dighe in esercizio\", \"Ufficio di coordinamento e controllo vigilanza lavori\", \"Ufficio di coordinamento Studi e Ricerche\"], \"keywords\": \"TABELLA\", \"roles\": null}"}
{"instruction": "extract event trigger and the entities involved in the event. Output is in JSON format", "context": "Le testate periodiche realizzate unicamente su supporto informatico e diffuse unicamente per via telematica ovvero on line, i cui editori non abbiano fatto domanda di provvidenze, contributi o agevolazioni pubbliche e che conseguano ricavi annui da attivita’ editoriale non superiori a 100.000 euro, non sono soggette agli obblighi stabiliti dall’articolo 5 della legge 8 febbraio 1948, n. 47, dall’articolo 1 della legge 5 agosto 1981, n. 416, e successive modificazioni, e dall’articolo 16 della legge 7 marzo 2001, n. 62, e ad esse non si applicano le disposizioni di cui alla delibera dell’Autorita’ per le garanzie nelle comunicazioni n. 666/08/CONS del 26 novembre 2008, e successive modificazioni.", "response": "{\"event_trigger\": \"non sono soggette\", \"legal_concepts\": [\"testate periodiche realizzate unicamente su supporto informatico e diffuse unicamente per via telematica\", \"provvidenze, contributi o agevolazioni pubbliche\", \"ricavi annui\", \"obblighi stabiliti\"], \"references\": [\"legge 8 febbraio 1948, n. 47\", \"legge 5 agosto 1981, n. 416\", \"legge 7 marzo 2001, n. 62\", \"articolo 16 della legge 7 marzo 2001, n. 62\", \"delibera dell’Autorita’ per le garanzie nelle comunicazioni n. 666/08/CONS del 26 novembre 2008\"], \"actors\": [\"testate periodiche\", \"editori\"], \"keywords\": [\"testate periodiche\", \"supporto informatico\", \"via telematica\", \"obblighi stabiliti\"]}"}
{"instruction": "extract event trigger, the entities involved, and the roles that entities have in the event or the relationships between them. Output is in JSON format", "context": "Orbene, come è già stato giudicato dalla Corte, il fatto che tale definizione colleghi l’esercizio di un’attività economica alla presenza di risorse umane dimostra che sono necessarie un minimo di organizzazione e una certa stabilità e che di conseguenza, a contrario, la mera presenza di singoli beni o di conti bancari non soddisfa, in linea di principio, i requisiti necessari ai fini della qualificazione come «dipendenza» (sentenza Interedil, C‑396/09, EU:C:2011:671, punto 62).", "response": "{\"event_trigger\": [\"dimostra che sono necessarie\", \"non soddisfa\"], \"legal_concepts\": [\"definizione\", \"esercizio di attività economica\", \"presenza di risorse umane\", \"organizzazione\", \"stabilità\", \"presenza di singoli beni o di conti bancari\", \"requisiti necessari\", \"qualificazione\", \"dipendenza\"], \"references\": \"sentenza Interedil, C‑396/09, EU:C:2011:671\", \"actors\": \"Corte\", \"keywords\": null, \"roles\": [{\"role_name\": \"agent\", \"argument1\": \"dimostra che sono necessarie\", \"argument2\": \"esercizio di attività economica\"}, {\"role_name\": \"agent\", \"argument1\": \"dimostra che sono necessarie\", \"argument2\": \"presenza di risorse umane\"}, {\"role_name\": \"theme\", \"argument1\": \"dimostra che sono necessarie\", \"argument2\": \"requisiti\"}, {\"role_name\": \"agent\", \"argument1\": \"non soddisfa\", \"argument2\": \"presenza di singoli beni o di conti bancari\"}, {\"role_name\": \"theme\", \"argument1\": \"non soddisfa\", \"argument2\": \"requisiti\"}, {\"role_name\": \"regulates\", \"argument1\": \"requisiti\", \"argument2\": [\"qualificazione\", \"dipendenza\"]}, {\"role_name\": \"regulates\", \"argument1\": \"sentenza Interedil, C‑396/09, EU:C:2011:671\", \"argument2\": \"dimostra\"}]}"}
{"instruction": "extract event trigger, the entities involved, and the roles that entities have in the event. Output is in JSON format", "context": "AVARINO. Il tempo di presentare la denuncia del furto che i carabinieri hanno recuperato il maltolto, restituendolo all'89enne disperata e amareggiata per come era stata derubata, in modo pressoché beffardo. I militari infatti, grazie anche alle sommarie descrizioni che la stessa anziana aveva fornito del ladro, sono in pratica andati a botta sicura. Nella cittadina infatti questo 53enne è figura conosciuta, le sue gesta sono quelle riportate in un lungo curriculum di precedenti con la giustizia. Probabilmente il malvivente, abituato ad altre esperienze ladresche più impegnative, non aveva dato troppa importanza all'anziana, che lo aveva visto in azione e che lui aveva pure salutato nell'allontanarsi a bordo della vettura. Una spavalderia dimostrata anche dal fatto che l'auto, la Fiat 500 che aveva rubato all'anziana, non l'aveva nascosta chissà dove o abbandonata dopo un utilizzo, ma se l'era messa tranquillamente in garage. I carabinieri pertanto, che si erano recati a casa del 53enne per effettuare un doveroso controllo perché insospettiti dopo la denuncia dell'89enne, hanno avuto gioco facile, trovando, recuperando e restituendo la 500 all'anziana. La signora in fase di denuncia, aveva raccontato ai militari che si trovava in cortile quando ha visto passare un uomo che, con estrema nonchalance, ha aperto la portiera della sua 500 e ha messo in moto. Le chiavi erano all'interno della vettura proprio accanto a casa: il ladro ha salutato e se ne è andato. Ma, come è poi risultato, non è andato lontano. Il 53enne è stato denunciato.", "response": "{\"event_trigger\": \"furto\", \"author_of_theft\": \"53enne\", \"victim_of_theft\": \"89enne\", \"location\": [\"Ravarino\", \"garage\"], \"object\": \"Fiat 500\", \"temporal_expressions\": null, \"organizations\": \"carabinieri\"}"}
{"instruction": "extract event trigger, the entities involved, and the roles that entities have in the event. Output is in JSON format", "context": "Brutta sorpresa, all'alba di ieri, per i gestori del bar della Polisportiva San Faustino. Alcuni ladri, dopo aver rotto un vetro, hanno vuotato la cassa e sono riusciti a scappare non appena è suonato l'allarme. Sul posto sono arrivate le forze dell'ordine. La polisportiva, che si affaccia su via Wiligelmo e al suo interno ha diverse attività, è stata così presa di mira da malviventi che cercano incursioni notturne in spazi ricreativi, di quartiere o scolastici, che tanto in questi mesi sono statio presi di mira. Più del furto pesano però certamente i danni, dal momento che l'effrazione porterà a cambiare infissi e vetri per migliaia di euro.", "response": "{\"event_trigger\": \"hanno vuotato\", \"author_of_theft\": \"alcuni ladri\", \"victim_of_theft\": \"gestori del bar della Polisportiva San Faustino\", \"location\": \"la polisportiva, che si affaccia su via Wiligelmo\", \"object\": \"la cassa\", \"temporal_expressions\": \"all'alba di ieri\", \"organizations\": [\"la Polisportiva San Faustino\", \"carabinieri\"]}"}
{"instruction": "extract event trigger, the entities involved, and the roles that entities have in the event. Output is in JSON format", "context": "La realizzazione del progetto di riqualificazione urbana, iniziativa ambiziosa del comune, ha coinvolto urbanisti, architetti e residenti in un processo partecipativo durato oltre un anno.", "response": "{\"event_trigger\": \"ha coinvolto\", \"events\": \"progetto di riqualificazione urbana\", \"people\": [\"urbanisti\", \"architetti\", \"residenti\"], \"actions\": \"realizzazione\", \"concepts\": [\"iniziativa ambiziosa\", \"processo partecipativo\"], \"time_expressions\": \"un anno\", \"roles\": [{\"role_name\": \"agent\", \"argument1\": \"ha coinvolto\", \"argument2\": \"progetto di riqualificazione urbana\"}, {\"role_name\": \"theme\", \"argument1\": \"ha coinvolto\", \"argument2\": [\"urbanisti\", \"architetti\", \"residenti\"]}, {\"role_name\": \"duration\", \"argument1\": \"un anno\", \"argument2\": \"progetto di riqualificazione urbana\"}]}"}
{"instruction": "extract event trigger, the entities involved, and the roles that entities have in the event. Output is in JSON format", "context": "MODENA Hanno tamponato con la loro auto e spinto per diversi metri una vettura, poi sono usciti dal veicolo su cui viaggiavano e si sono allontanati in fretta a piedi, davanti a un'incredulità del conducente dell'altro mezzo coinvolto, che ha subito chiamato la Polizia municipale di Modena. Gli agenti, giunti in viale Vittorio Emanuele dove domenica 31 marzo verso le 21 si è verificato il sinistro, hanno subito capito i motivi di tale comportamento. L'auto abbandonata, un Opel Agila, presentava evidenti segni di scasso e, all'interno, erano in bella vista i cavi elettrici dell'accensione, utilizzati per metterla in moto senza le chiavi. Dagli accertamenti è infatti risultato che la vettura era stata rubata a Carpi una settimana prima e il furto regolarmente denunciato. Secondo il racconto dell'altro conducente, un romano in visita a Modena, l'Opel Agila sarebbe giunta a tutta velocità su viale Vittorio Veneto in direzione Accademia e avrebbe urtato violentemente la Fiat 500 intenta a spostarsi verso sinistra per parcheggiare, fortunatamente illeso il conducente. L'auto rubata è ora a disposizione della Polizia Scientifica per eventuali rilievi, poi sarà restituita al legittimo proprietario, mentre la Polizia Municipale ha acquisito le immagini della telecamera di videosorveglianza che potrebbe aver ripreso l'incidente per verificare elementi utili a risalire all'identità delle due persone che l'hanno abbandonata: un uomo di mezz'età che era alla guida e la passeggera, una ragazza più giovane.", "response": "{\"event_trigger\": \"era stata rubata\", \"author_of_theft\": [\"uomo di mezz'età\", \"ragazza più giovane\"], \"victim_of_theft\": \"legittimo proprietario\", \"location\": \"Carpi\", \"object\": \"l'auto, un Opel Agila\", \"temporal_expressions\": \"una settimana prima\", \"organizations\": [\"Polizia Scientifica\", \"Polizia Municipale\"]}"}
{"instruction": "extract event trigger and the entities involved in the event. Output is in JSON format", "context": "Fermo restando quanto previsto ai fini della procedura di Valutazione ambientale strategica (VAS), il Piano è costituito dai seguenti elaborati: a) quadro di analisi conoscitivo, suddiviso per bacini di utenza, volto all’analisi della consistenza dei giacimenti in essere sul territorio regionale; b) quadro operativo, che individua i poli estrattivi, i siti per il deposito dei rifiuti di estrazione ardesiaci e le zone ove è consentita la realizzazione di opere in superficie delle cave in sotterraneo, quali imbocchi, strade di servizio, piazzali; c) norme di attuazione, che prevedono in particolare le modalità, le indicazioni e le condizioni per l'esercizio dell'attività estrattiva e per la sistemazione finale dei siti; d) documento di definizione dei contenuti fondamentali del Piano, per la modifica dei quali è necessaria una variante sostanziale, ai sensi dell'articolo 6, comma 1; e) piano di monitoraggio.", "response": "{\"event_trigger\": \"è costituito\", \"legal_concepts\": [\"Piano\", \"procedura di Valutazione ambientale strategica (VAS)\", \"quadro di analisi conoscitivo\", \"quadro operativo\", \"norme di attuazione\", \"documento di definizione dei contenuti fondamentali\", \"piano di monitoraggio\"], \"references\": \"articolo 6, comma 1\", \"actors\": null, \"keywords\": [\"bacini di utenza\", \"territorio regionale\", \"analisi della consistenza dei giacimenti\", \"poli estrattivi\", \"siti per il deposito dei rifiuti di estrazione ardesiaci\", \"zone ove è consentita la realizzazione di opere in superficie delle cave in sotterraneo\", \"imbocchi\", \"strade di servizio\", \"piazzali\", \"condizioni per l'esercizio\", \"sistemazione finale dei siti\", \"modifica\"]}"}
{"instruction": "extract event trigger, the entities involved, and the roles that entities have in the event or the relationships between them. Output is in JSON format", "context": "Secondo: l’ordinamento deve consentire che qualche particolare azione strumentale che durante la fase deliberativa aveva pensato essere corretta si riveli di fatto scorretta, o viceversa, se uno dei partecipanti sia in grado di provarlo in seguito.", "response": "{\"event_trigger\": [\"consentire\", \"si riveli\"], \"legal_concepts\": [\"ordine giuridico\", \"azione strumentale\", \"fase deliberativa\", \"corretta\", \"scorretta\"], \"references\": null, \"actors\": \"partecipanti\", \"keywords\": null, \"roles\": [{\"role_name\": \"agent\", \"argument1\": \"consentire\", \"argument2\": \"ordinamento\"}, {\"role_name\": \"theme\", \"argument1\": \"consentire\", \"argument2\": \"azione strumentale\"}, {\"role_name\": \"agent\", \"argument1\": \"si riveli\", \"argument2\": \"azione strumentale\"}, {\"role_name\": \"theme\", \"argument1\": \"si riveli\", \"argument2\": \"scorretta\"}]}"}
{"instruction": "extract event trigger, the entities involved, and the roles that entities have in the event. Output is in JSON format", "context": "Un flashmob sorpresa ha animato la piazza principale della città.", "response": "{\"event_trigger\": \"ha animato\", \"events\": \"flashmob sorpresa\", \"places\": \"piazza principale della città\", \"roles\": [{\"role_name\": \"agent\", \"argument1\": \"ha animato\", \"argument2\": \"Un flashmob sorpresa\"}, {\"role_name\": \"theme\", \"argument1\": \"ha animato\", \"argument2\": \"piazza principale della città\"}]}"}
{"instruction": "extract event trigger, the entities involved, and the roles that entities have in the event or the relationships between them. Output is in JSON format", "context": "Utilizzo di aeromobili a pilotaggio remoto da parte del Corpo di polizia penitenziaria 1. All'articolo 5, comma 3-sexies, del decreto-legge 18 febbraio 2015, n. 7, convertito, con modificazioni, dalla legge 17 aprile 2015, n. 43, e' aggiunto, in fine, il seguente periodo: «L'utilizzo di aeromobili a pilotaggio remoto da parte del personale abilitato del Corpo di polizia penitenziaria e' previsto nell'ambito delle funzioni svolte dal predetto personale ai sensi dell'articolo 5 della legge 15 dicembre 1990, n. 395, per assicurare una piu' efficace vigilanza sugli istituti penitenziari e garantire la sicurezza all'interno dei medesimi». 2. All'attuazione delle disposizioni del presente articolo si provvede con le risorse umane, finanziarie e strumentali disponibili a legislazione vigente, senza nuovi o maggiori oneri a carico della finanza pubblica.", "response": "{\"event_trigger\": \"è aggiunto\", \"legal_concepts\": \"Utilizzo di aeromobili a pilotaggio remoto\", \"references\": [\"ARTICOLO AGGIUNTO DALLA LEGGE DI CONVERSIONE 25/6/2020, N. 70\", \"articolo 5, comma 3-sexies, del decreto-legge 18 febbraio 2015, n. 7\", \"legge 17 aprile 2015, n. 43\"], \"actors\": \"Corpo di polizia penitenziaria\", \"keywords\": \"periodo\", \"roles\": [{\"role_name\": \"agent\", \"argument1\": \"è aggiunto\", \"argument2\": \"articolo 5, comma 3-sexies, del decreto-legge 18 febbraio 2015, n. 7\"}, {\"role_name\": \"theme\", \"argument1\": \"è aggiunto\", \"argument2\": \"periodo\"}, {\"role_name\": \"regulates\", \"argument1\": \"periodo\", \"argument2\": \"Utilizzo di aeromobili a pilotaggio remoto\"}, {\"role_name\": \"regulates\", \"argument1\": \"articolo 5 della legge 15 dicembre 1990, n. 395\", \"argument2\": \"Utilizzo di aeromobili a pilotaggio remoto\"}]}"}
{"instruction": "extract event trigger, the entities involved, and the roles that entities have in the event or the relationships between them. Output is in JSON format", "context": "In sede di procedimento elettorale negli Enti locali siciliani, l'art. 3 comma 6 L. reg.", "response": "{\"event_trigger\": \"procedimento elettorale negli Enti locali siciliani\", \"legal_concepts\": \"Enti locali siciliani\", \"references\": \"art. 3 comma 6 L. reg.\", \"actors\": null, \"keywords\": null, \"roles\": [{\"role_name\": \"regulates\", \"argument1\": \"art. 3 comma 6 L. reg.\", \"argument2\": \"Enti locali siciliani\"}]}"}
{"instruction": "extract event trigger, the entities involved, and the roles that entities have in the event or the relationships between them. Output is in JSON format", "context": "Peraltro, si dà atto dell'intervento di un membro supplente, non indicando i tre componenti, né si fa sua menzione dalla specificazione del membro effettivo sostituito.", "response": "{\"event_trigger\": \"si dà atto dell'intervento\", \"legal_concepts\": null, \"references\": null, \"actors\": [\"membro supplente\", \"membro effettivo sostituito\"], \"keywords\": null, \"roles\": [{\"role_name\": \"theme\", \"argument1\": \"si dà atto dell'intervento\", \"argument2\": \"un membro supplente\"}]}"}
{"instruction": "extract event trigger, the entities involved, and the roles that entities have in the event. Output is in JSON format", "context": "Dopo mesi di intensa preparazione e pianificazione logistica, l'evento benefico annuale per la raccolta fondi ha finalmente preso il via, coinvolgendo centinaia di volontari e donatori provenienti da diverse parti del paese.", "response": "{\"event_trigger\": \"ha preso il via\", \"events\": \"evento benefico annuale\", \"people\": \"volontari e donatori\", \"actions\": [\"preparazione\", \"pianificazione\", \"raccolta fondi\"], \"places\": \"diverse parti del paese\", \"time_expressions\": \"mesi\", \"roles\": [{\"role_name\": \"agent\", \"argument1\": \"ha preso il via\", \"argument2\": \"evento benefico annuale\"}, {\"role_name\": \"theme\", \"argument1\": \"ha preso il via\", \"argument2\": \"volontari e donatori\"}, {\"role_name\": \"goal\", \"argument1\": \"evento benefico annuale\", \"argument2\": \"raccola fondi\"}, {\"role_name\": \"succeed\", \"argument1\": \"ha preso il via\", \"argument2\": [\"preparazione\", \"pianificazione\"]}, {\"role_name\": \"duration\", \"argument1\": \"mesi\", \"argument2\": [\"preparazione\", \"pianificazione\"]}, {\"role_name\": \"origin\", \"argument1\": \"volontari e donatori\", \"argument2\": \"diverse parti del paese\"}]}"}
{"instruction": "extract event trigger and the entities involved in the event. Output is in JSON format", "context": "La Regione riconosce i Centri per la conservazione, la riproduzione, il recupero e il ricovero di specie animali e vegetali di interesse regionale e definisce, secondo quanto previsto dalla lettera e) del comma 1 dell'articolo 12, i requisiti strutturali degli stessi, nonché i requisiti organizzativi e strumentali il cui possesso deve essere accertato in capo ai soggetti interessati, anche ai fini dell'erogazione di eventuali finanziamenti. 2. I Centri di conservazione della fauna selvatica riconosciuti ai sensi del presente articolo possono essere riconosciuti anche quali Centri di recupero della fauna selvatica di cui all'articolo 38 della legge regionale 3/1994. Tali centri potranno altresì essere organizzati per la detenzione delle specie di cui è vietato il rilascio in natura ai sensi della legge 7 febbraio 1992, n. 150 e successive modificazioni e integrazioni, delle specie di cui al all'art. 5, comma 6, e di quelle sottoposte ad affidamento in custodia ai sensi dell'art.17, comma 8, della presente legge.", "response": "{\"event_trigger\": [\"riconosce\", \"potranno altresì essere organizzati\"], \"legal_concepts\": [\"Centri per la conservazione di specie animali e vegetali\", \"requisiti strutturali, organizzativi e strumentali\", \"Centri di recupero della fauna selvatica\", \"detenzione delle specie di cui è vietato il rilascio\"], \"references\": [\"lettera e del comma 1 dell'articolo 12\", \"articolo 38 della legge regionale 3/1994\", \"legge 7 febbraio 1992, n. 150\", \"art. 5, comma 6\", \"art.17, comma 8, della presente legge\"], \"actors\": \"Regione\", \"keywords\": \"erogazione di eventuali finanziamenti\"}"}
